{"id":120327430,"topNeighbourId":120327431,"bottomNeighbourId":120327429,"leftNeighbourId":120326918,"rightNeighbourId":120327942,"shadowBonusOnEntities":-1,"cells":[{"l":2},{"l":2},{"l":2},{"l":2},{"l":2},{"l":2},{"l":66},{"l":66},{"l":66},{"l":66},{"l":66},{"l":2},{"l":2},{"l":2},{"l":2},{"l":2},{"l":2},{"l":2},{"l":2},{"l":2},{"l":66},{"l":66},{"l":66},{"l":66},{"l":2},{"l":2},{"l":2},{"l":2},{"l":2},{"l":2},{"l":2},{"l":2},{"l":2},{"l":2},{"l":66},{"l":66},{"l":66},{"l":66},{"l":66},{"l":2},{"l":2},{"l":2},{"l":2},{"l":2},{"l":2},{"l":2},{"l":2},{"l":66},{"l":66},{"l":66},{"l":66},{"l":66},{"l":66},{"l":2},{"l":2},{"l":2},{"l":2},{"l":2},{"l":2},{"l":2},{"l":2},{"l":2},{"l":66},{"l":66},{"l":66},{"l":66},{"l":66},{"l":2},{"l":2},{"l":2},{"l":2},{"l":2},{"l":2},{"l":2},{"l":2},{"l":66},{"l":66},{"l":66},{"l":66},{"l":66},{"l":66},{"l":2},{"l":2},{"l":2},{"l":2},{"l":2},{"l":2},{"l":2},{"l":2},{"l":2},{"l":66},{"l":66},{"l":66},{"l":66},{"l":66},{"l":66},{"l":2},{"l":2},{"l":2},{"l":2},{"l":2},{"l":2},{"l":2},{"l":66},{"l":66},{"l":66},{"l":66},{"l":66},{"l":66},{"l":2},{"l":2},{"l":2},{"l":2},{"l":2},{"l":2},{"l":2},{"l":2},{"l":2},{"l":66},{"l":66},{"l":66},{"l":66},{"l":66},{"l":66},{"l":2},{"l":2},{"l":2},{"l":2},{"l":2},{"l":2},{"l":2},{"l":66},{"l":67},{"l":66},{"l":66},{"l":66},{"l":66},{"l":66},{"l":66},{"l":2},{"l":2},{"l":2},{"l":2},{"l":2},{"l":2},{"l":66},{"l":67},{"l":67},{"l":66},{"l":66},{"l":66},{"l":66},{"l":66},{"l":2},{"l":2},{"l":2},{"l":2},{"l":2},{"l":66},{"l":67},{"l":67},{"l":67},{"l":66},{"l":66},{"l":66},{"l":66},{"l":66},{"l":2},{"l":2},{"l":2},{"l":2},{"l":2},{"l":66},{"l":67},{"l":67},{"l":67},{"l":67},{"l":66},{"l":66},{"l":66},{"l":66},{"l":66},{"l":2},{"l":2},{"l":2},{"l":66},{"l":67},{"l":67},{"l":67},{"l":67},{"l":67},{"l":66},{"l":66},{"l":66},{"l":66},{"l":2},{"l":2},{"l":2},{"l":2},{"l":2},{"l":67},{"l":67},{"l":67},{"l":67},{"l":67},{"l":67},{"l":66},{"l":66},{"l":66},{"l":66},{"l":2},{"l":2},{"l":66},{"l":67},{"l":67},{"l":67},{"l":67},{"l":67},{"l":67},{"l":67},{"l":66},{"l":66},{"l":66},{"l":2},{"l":2},{"l":2},{"l":66},{"l":67},{"l":67},{"l":67},{"l":67},{"l":67},{"l":67},{"l":67},{"l":67},{"l":66},{"l":66},{"l":66},{"l":2},{"l":2},{"l":67},{"l":67},{"l":67},{"l":67},{"l":67},{"l":67},{"l":67},{"l":67},{"l":67},{"l":66},{"l":66},{"l":2},{"l":2},{"l":2},{"l":67},{"l":67},{"l":67},{"l":67},{"l":67},{"l":67},{"l":67},{"l":67},{"l":67},{"l":67},{"l":66},{"l":2},{"l":2},{"l":67},{"l":67},{"l":67},{"l":67},{"l":67},{"l":67},{"l":67},{"l":67},{"l":67},{"l":67},{"l":67},{"l":66},{"l":2},{"l":2},{"l":3},{"l":67},{"l":67},{"l":67},{"l":67},{"l":67},{"l":67},{"l":67},{"l":67},{"l":67},{"l":67},{"l":67},{"l":2},{"l":2},{"l":3},{"l":67},{"l":67},{"l":67},{"l":67},{"l":67},{"l":67},{"l":67},{"l":67},{"l":67},{"l":67},{"l":3},{"l":2},{"l":2},{"l":2},{"l":67},{"l":67},{"l":67},{"l":67},{"l":67},{"l":67},{"l":67},{"l":67},{"l":67},{"l":67},{"l":67},{"l":2},{"l":2},{"l":3},{"l":67},{"l":67},{"l":67},{"l":67},{"l":67},{"l":67},{"l":67},{"l":67},{"l":67},{"l":67},{"l":2},{"l":2},{"l":2},{"l":3},{"l":67},{"l":67},{"l":67},{"l":67},{"l":67},{"l":67},{"l":67},{"l":67},{"l":67},{"l":67},{"l":67},{"l":2},{"l":2},{"l":3},{"l":67},{"l":67},{"l":67},{"l":67},{"l":67},{"l":67},{"l":67},{"l":67},{"l":67},{"l":67},{"l":67},{"l":2},{"l":2},{"l":2},{"l":3},{"l":67},{"l":67},{"l":67},{"l":67},{"l":67},{"l":67},{"l":67},{"l":67},{"l":67},{"l":67},{"l":2},{"l":2},{"l":2},{"l":3},{"l":67},{"l":67},{"l":67},{"l":67},{"l":67},{"l":67},{"l":67},{"l":67},{"l":67},{"l":66},{"l":2},{"l":2},{"l":2},{"l":2},{"l":3},{"l":67},{"l":67},{"l":67},{"l":67},{"l":67},{"l":67},{"l":67},{"l":67},{"l":66},{"l":2},{"l":2},{"l":2},{"l":2},{"l":3},{"l":67},{"l":67},{"l":67},{"l":67},{"l":67},{"l":67},{"l":67},{"l":66},{"l":66},{"l":2},{"l":2},{"l":2},{"l":2},{"l":2},{"l":3},{"l":67},{"l":67},{"l":67},{"l":67},{"l":67},{"l":67},{"l":66},{"l":2},{"l":2},{"l":2},{"l":2},{"l":2},{"l":2},{"l":67},{"l":67},{"l":67},{"l":67},{"l":67},{"l":67},{"l":66},{"l":2},{"l":2},{"l":2},{"l":2},{"l":2},{"l":2},{"l":2},{"l":2},{"l":67},{"l":67},{"l":67},{"l":67},{"l":67},{"l":66},{"l":2},{"l":2},{"l":2},{"l":2},{"l":2},{"l":2},{"l":2},{"l":2},{"l":67},{"l":67},{"l":67},{"l":67},{"l":66},{"l":2},{"l":2},{"l":2},{"l":2},{"l":2},{"l":2},{"l":2},{"l":2},{"l":2},{"l":66},{"l":67},{"l":67},{"l":67},{"l":2},{"l":66},{"l":2},{"l":2},{"l":2},{"l":2},{"l":2},{"l":2},{"l":2},{"l":2},{"l":66},{"l":67},{"l":67},{"l":2},{"l":2},{"l":2},{"l":2},{"l":2},{"l":2},{"l":2},{"l":2},{"l":2},{"l":2},{"l":2},{"l":2},{"l":66},{"l":67},{"l":66},{"l":2},{"l":2},{"l":2},{"l":2},{"l":2},{"l":2},{"l":2},{"l":2},{"l":2},{"l":2},{"l":2},{"l":66},{"l":66},{"l":2},{"l":2},{"l":2},{"l":2},{"l":2},{"l":2},{"l":2},{"l":2},{"l":2},{"l":2},{"l":2},{"l":2},{"l":2},{"l":66},{"l":66},{"l":2},{"l":2},{"l":2},{"l":2},{"l":2},{"l":2},{"l":2},{"l":2},{"l":2},{"l":2},{"l":2},{"l":2},{"l":66},{"l":66},{"l":2},{"l":2},{"l":2},{"l":2},{"l":2}],"midgroundLayer":{"144":[{"g":61015,"x":20,"y":-71,"hue":[-23,-34,-70],"cy":-56,"cw":371,"ch":298}],"145":[{"g":62798,"x":369,"y":204,"hue":[-1,-19,-70],"cw":63,"ch":35}],"156":[{"g":62801,"x":180,"y":79.5,"hue":[-26,-42,-83],"cw":29,"ch":17}],"157":[{"g":47524,"x":385,"y":210.5,"hue":[-4,-13,-47],"sx":-1,"cw":82,"ch":47}],"170":[{"g":47524,"x":213,"y":233,"hue":[0,0,0],"sx":-1,"cw":82,"ch":47}],"172":[{"g":57968,"x":604,"y":-298,"hue":[-52,-58,-79],"sx":-1,"cw":657,"ch":679}],"182":[{"g":43278,"x":-203,"y":-115.5,"hue":[-24,-31,-56],"cx":-150,"cy":-100,"cw":224,"ch":381}],"184":[{"g":47528,"x":272,"y":226.5,"hue":[-19,-27,-57],"sx":-1,"cw":94,"ch":70}],"185":[{"g":62800,"x":280,"y":136.5,"hue":[-26,-42,-83],"cw":49,"ch":30}],"199":[{"g":51929,"x":215,"y":258,"hue":[2,-7,-49],"cw":87,"ch":74}],"209":[{"g":43277,"x":996,"y":-104,"hue":[-1,-16,-56],"cy":-89,"cw":218,"ch":332}],"224":[{"g":51923,"x":-39,"y":197,"hue":[-1,-4,-35],"cw":282,"ch":191}],"225":[{"g":43261,"x":-60,"y":224,"hue":[-17,-27,-56],"cw":213,"ch":171}],"238":[{"g":62918,"x":-36,"y":188.5,"hue":[-19,-27,-57],"cw":151,"ch":133},{"g":62907,"x":153,"y":216.5,"hue":[-19,-27,-57],"sx":-1,"cw":150,"ch":147}],"252":[{"g":62918,"x":-104,"y":213,"hue":[-19,-27,-57],"cw":151,"ch":133},{"g":62919,"x":-32,"y":258,"hue":[-19,-27,-57],"cw":79,"ch":100}],"253":[{"g":51925,"x":38,"y":330,"hue":[-19,-27,-57],"cw":95,"ch":89}],"266":[{"g":43293,"x":-183,"y":285.5,"hue":[-23,-30,-56],"cw":253,"ch":183},{"g":47528,"x":123,"y":389.5,"hue":[-19,-27,-57],"sx":-1,"cw":94,"ch":70}],"280":[{"g":47524,"x":-51,"y":429,"hue":[-19,-27,-57],"cw":82,"ch":47}],"294":[{"g":51926,"x":-6,"y":380.5,"hue":[-19,-27,-57],"cw":104,"ch":102}],"306":[{"g":44498,"x":1049,"y":355.5,"hue":[0,0,0],"cw":67,"ch":121}],"307":[{"g":43260,"x":1088,"y":513.5,"hue":[-25,-33,-58],"cw":126,"ch":168}],"309":[{"g":51928,"x":45,"y":416,"hue":[-19,-27,-57],"cw":83,"ch":82}],"321":[{"g":43267,"x":1058,"y":80,"hue":[-8,-20,-56],"cw":156,"ch":510}],"322":[{"g":51929,"x":-13,"y":436.5,"hue":[-19,-27,-57],"cw":87,"ch":74},{"g":62920,"x":-13,"y":-1.5,"hue":[-19,-27,-57],"cw":105,"ch":98}],"363":[{"g":55717,"x":1163,"y":534.5,"hue":[-19,-27,-57],"cw":29,"ch":17}],"471":[{"g":55715,"x":816,"y":692.5,"hue":[-19,-19,-46],"cw":47,"ch":35}],"505":[{"g":62920,"x":30,"y":616,"hue":[-19,-27,-57],"cw":105,"ch":98}],"560":[{"g":43262,"x":739,"y":726,"hue":[-32,-39,-66],"cw":98,"ch":78},{"g":44443,"x":681,"y":739.5,"hue":[-42,-48,-72],"cw":102,"ch":75},{"g":55716,"x":877,"y":782.5,"hue":[0,0,0],"cw":31,"ch":19},{"g":62801,"x":916,"y":666,"hue":[-29,-36,-76],"cw":29,"ch":17},{"g":61018,"x":875,"y":745,"hue":[-24,-31,-56],"cw":295,"ch":106},{"g":57968,"x":729,"y":535.5,"hue":[-128,-128,-128],"cw":657,"ch":679},{"g":43261,"x":723,"y":775.5,"hue":[-42,-48,-69],"cw":213,"ch":171},{"g":43280,"x":567,"y":750.5,"hue":[-24,-31,-56],"sx":-1,"cw":185,"ch":100},{"g":43293,"x":429,"y":809.5,"hue":[-42,-49,-58],"cw":253,"ch":183},{"g":38625,"x":631,"y":775,"hue":[0,0,0],"sx":3.382,"sy":3.382,"cx":203,"cy":234,"cw":541,"ch":475},{"g":38625,"x":631,"y":775,"hue":[0,0,0],"sx":3.382,"sy":3.382,"cx":203,"cy":234,"cw":541,"ch":475},{"g":38625,"x":631,"y":775,"hue":[0,0,0],"sx":3.382,"sy":3.382,"alpha":0.7058823529411765,"cx":203,"cy":234,"cw":541,"ch":475},{"g":38625,"x":-149,"y":-108,"hue":[0,0,0],"sx":2.19,"sy":2.19,"rotation":-0.5174901232163187,"cx":203,"cy":234,"cw":541,"ch":475},{"g":38625,"x":-149,"y":-108,"hue":[0,0,0],"sx":2.19,"sy":2.19,"rotation":-0.5174901232163187,"cx":203,"cy":234,"cw":541,"ch":475},{"g":38625,"x":-149,"y":-108,"hue":[0,0,0],"sx":2.19,"sy":2.19,"rotation":-0.5174901232163187,"alpha":0.7490196078431373,"cx":203,"cy":234,"cw":541,"ch":475},{"g":51033,"x":222,"y":722,"hue":[0,0,0],"sx":1.613,"sy":1.613,"rotation":1.0445795573186063,"alpha":0.4,"cx":672,"cy":289,"cw":932,"ch":477},{"g":51033,"x":135,"y":1128,"hue":[0,0,0],"sx":1.613,"sy":1.613,"rotation":1.0445795573186063,"alpha":0.4,"cx":672,"cy":289,"cw":932,"ch":477}]},"atlasLayout":{"width":759,"height":1063,"graphicsPositions":{"38625":{"sx":202,"sy":989,"sw":81,"sh":71,"cx":284,"cy":7,"cw":541,"ch":475},"43260":{"sx":153,"sy":750,"sw":126,"sh":168},"43261":{"sx":221,"sy":577,"sw":213,"sh":171},"43262":{"sx":382,"sy":908,"sw":98,"sh":78},"43267":{"sx":600,"sy":1,"sw":156,"sh":510},"43277":{"sx":1,"sy":301,"sw":218,"sh":332,"cy":89},"43278":{"sx":374,"sy":1,"sw":224,"sh":381,"cx":150,"cy":100},"43280":{"sx":434,"sy":806,"sw":185,"sh":100},"43293":{"sx":505,"sy":513,"sw":253,"sh":183},"44443":{"sx":98,"sy":920,"sw":102,"sh":75},"44498":{"sx":505,"sy":384,"sw":67,"sh":121},"47524":{"sx":285,"sy":989,"sw":82,"sh":47},"47528":{"sx":1,"sy":979,"sw":94,"sh":70},"51033":{"sx":221,"sy":301,"sw":140,"sh":72,"cx":11,"cw":932,"ch":477},"51923":{"sx":221,"sy":384,"sw":282,"sh":191},"51925":{"sx":1,"sy":888,"sw":95,"sh":89},"51926":{"sx":1,"sy":784,"sw":104,"sh":102},"51928":{"sx":482,"sy":908,"sw":83,"sh":82},"51929":{"sx":382,"sy":988,"sw":87,"sh":74},"55715":{"sx":153,"sy":635,"sw":47,"sh":35},"55716":{"sx":382,"sy":885,"sw":31,"sh":19},"55717":{"sx":233,"sy":957,"sw":29,"sh":17},"57968":{"sx":281,"sy":885,"sw":99,"sh":102,"cw":657,"ch":679},"61015":{"sx":1,"sy":1,"sw":371,"sh":298,"cy":56},"61018":{"sx":436,"sy":698,"sw":295,"sh":106},"62798":{"sx":202,"sy":920,"sw":63,"sh":35},"62800":{"sx":98,"sy":888,"sw":49,"sh":30},"62801":{"sx":202,"sy":957,"sw":29,"sh":17},"62907":{"sx":1,"sy":635,"sw":150,"sh":147},"62918":{"sx":281,"sy":750,"sw":151,"sh":133},"62919":{"sx":621,"sy":906,"sw":79,"sh":100},"62920":{"sx":621,"sy":806,"sw":105,"sh":98}}}}