{"id":125570054,"topNeighbourId":125570053,"bottomNeighbourId":125570055,"leftNeighbourId":125569542,"rightNeighbourId":125570566,"shadowBonusOnEntities":-1,"cells":[{"l":66},{"l":66},{"l":66},{"l":66},{"l":66},{"l":66},{"l":66},{"l":66},{"l":66},{"l":66},{"l":66},{"l":66},{"l":66},{"l":66},{"l":66},{"l":66},{"l":66},{"l":66},{"l":66},{"l":66},{"l":66},{"l":66},{"l":66},{"l":66},{"l":66},{"l":66},{"l":66},{"l":66},{"l":66},{"l":66},{"l":66},{"l":66},{"l":66},{"l":66},{"l":66},{"l":66},{"l":66},{"l":66},{"l":66},{"l":66},{"l":66},{"l":66},{"l":66},{"l":66},{"l":66},{"l":66},{"l":66},{"l":66},{"l":66},{"l":66},{"l":66},{"l":66},{"l":66},{"l":66},{"l":66},{"l":66},{"l":66},{"l":66},{"l":66},{"l":66},{"l":66},{"l":66},{"l":66},{"l":66},{"l":66},{"l":66},{"l":66},{"l":66},{"l":66},{"l":66},{"l":66},{"l":66},{"l":66},{"l":66},{"l":66},{"l":66},{"l":66},{"l":66},{"l":66},{"l":66},{"l":66},{"l":66},{"l":66},{"l":66},{"l":66},{"l":66},{"l":66},{"l":66},{"l":66},{"l":66},{"l":66},{"l":66},{"l":66},{"l":66},{"l":66},{"l":66},{"l":66},{"l":66},{"l":66},{"l":66},{"l":66},{"l":66},{"l":66},{"l":66},{"l":66},{"l":66},{"l":66},{"l":66},{"l":66},{"l":66},{"l":66},{"l":66},{"l":66},{"l":66},{"l":66},{"l":66},{"l":66},{"l":66},{"l":66},{"l":66},{"l":66},{"l":66},{"l":66},{"l":66},{"l":66},{"l":66},{"l":66},{"l":66},{"l":66},{"l":66},{"l":66},{"l":66},{"l":66},{"l":66},{"l":66},{"l":66},{"l":66},{"l":66},{"l":66},{"l":66},{"l":66},{"l":66},{"l":66},{"l":66},{"l":66},{"l":66},{"l":66},{"l":66},{"l":66},{"l":66},{"l":66},{"l":66},{"l":66},{"l":66},{"l":66},{"l":66},{"l":66},{"l":66},{"l":66},{"l":66},{"l":66},{"l":2},{"l":2},{"l":66},{"l":66},{"l":66},{"l":66},{"l":66},{"l":66},{"l":66},{"l":66},{"l":66},{"l":66},{"l":66},{"l":66},{"l":2},{"l":2},{"l":2},{"l":66},{"l":66},{"l":66},{"l":66},{"l":66},{"l":66},{"l":66},{"l":66},{"l":66},{"l":66},{"l":2},{},{},{"l":66},{"l":66},{"l":66},{"l":66},{"l":66},{"l":66},{"l":66},{"l":66},{"l":66},{"l":66},{"l":66},{"l":2},{},{},{"l":67},{"l":66},{"l":66},{"l":66},{"l":66},{"l":66},{"l":66},{"l":66},{"l":2},{"l":66},{"l":2},{},{"l":67},{"l":67},{"l":67},{"l":66},{"l":66},{"l":66},{"l":66},{"l":66},{"l":66},{"l":66},{"l":67},{"l":2},{"l":2},{},{"l":67},{"l":67},{"l":67},{"l":67},{"l":2},{"l":66},{"l":66},{"l":66},{"l":66},{"l":67},{"l":83},{"l":2},{},{"l":67},{"l":67},{"l":67},{"l":67},{"l":3},{"l":2},{"l":66},{"l":66},{"l":66},{"l":66},{"l":67},{"l":67},{"l":3},{},{"l":67},{"l":83},{"l":67},{"l":83},{"l":3},{},{"l":66},{"l":66},{"l":66},{"l":67},{"l":67},{"l":67},{},{"l":2},{"l":67},{"l":67},{"l":67},{"l":3},{},{"l":66},{"l":66},{"l":66},{"l":66},{"l":67},{"l":67},{"l":67},{},{"l":67},{"l":67},{"l":67},{"l":83},{"l":3},{},{"l":66},{"l":66},{"l":66},{"l":66},{"l":83},{"l":67},{"l":67},{"l":67},{"l":67},{"l":67},{"l":67},{"l":3},{},{"l":2},{"l":66},{"l":66},{"l":66},{"l":66},{"l":66},{"l":67},{"l":83},{"l":67},{"l":67},{"l":67},{"l":67},{"l":67},{},{},{"l":2},{"l":66},{"l":66},{"l":66},{"l":67},{"l":67},{"l":67},{"l":67},{"l":67},{"l":67},{"l":67},{},{},{"l":67},{"l":2},{"l":66},{"l":66},{"l":66},{"l":2},{"l":67},{"l":67},{"l":67},{"l":67},{"l":67},{"l":67},{"l":67},{},{"l":67},{"l":67},{"l":2},{"l":66},{"l":66},{"l":2},{"l":67},{"l":67},{"l":67},{"l":67},{"l":67},{"l":67},{"l":67},{"l":67},{"l":75},{"l":67},{"l":2},{"l":66},{"l":66},{"l":66},{"l":2},{"l":67},{"l":67},{"l":67},{"l":67},{"l":67},{"l":67},{"l":67},{"l":67},{"l":75},{"l":67},{"l":66},{"l":66},{"l":66},{"l":2},{"l":67},{"l":67},{"l":67},{"l":67},{"l":67},{"l":67},{"l":75},{"l":67},{"l":67},{"l":66},{"l":66},{"l":66},{"l":66},{"l":66},{"l":2},{"l":67},{"l":67},{"l":67},{"l":67},{"l":67},{"l":67},{"l":67},{"l":67},{"l":66},{"l":66},{"l":66},{"l":66},{"l":66},{"l":67},{"l":67},{"l":67},{"l":67},{"l":67},{"l":75},{"l":67},{"l":67},{"l":66},{"l":66},{"l":66},{"l":66},{"l":66},{"l":66},{"l":66},{"l":67},{"l":3},{"l":67},{"l":67},{"l":67},{"l":67},{"l":67},{"l":66},{"l":66},{"l":66},{"l":66},{"l":66},{"l":66},{"l":66},{"l":67},{"l":2},{"l":67},{"l":67},{"l":67},{"l":67},{"l":66},{"l":66},{"l":66},{"l":66},{"l":66},{"l":66},{"l":66},{"l":66},{"l":66},{},{"l":3},{"l":75},{"l":75},{"l":2},{"l":66},{"l":66},{"l":66},{"l":66},{"l":66},{"l":66},{"l":66},{"l":66},{"l":66},{},{"l":67},{"l":67},{"l":67},{"l":66},{"l":66},{"l":66},{"l":66},{"l":66},{"l":66},{"l":66},{"l":66},{"l":66},{"l":66},{"l":66},{"l":2},{"l":67},{"l":67},{"l":66},{"l":66},{"l":66},{"l":66},{"l":66},{"l":66},{"l":66},{"l":66},{"l":66},{"l":66},{"l":66},{"l":2},{"l":67},{"l":66},{"l":66},{"l":66},{"l":66},{"l":66},{"l":66},{"l":66},{"l":66},{"l":66},{"l":66},{"l":66},{"l":66},{"l":66},{"l":2},{"l":66},{"l":66},{"l":66},{"l":66},{"l":66},{"l":66},{"l":66},{"l":66},{"l":66},{"l":66},{"l":66},{"l":66},{"l":66},{"l":66},{"l":66},{"l":66},{"l":66},{"l":66},{"l":66},{"l":66},{"l":66},{"l":66},{"l":66},{"l":66},{"l":66},{"l":66},{"l":66},{"l":66},{"l":66},{"l":66},{"l":66},{"l":66},{"l":66},{"l":66},{"l":66},{"l":66},{"l":66},{"l":66},{"l":66},{"l":66},{"l":66},{"l":66},{"l":66},{"l":66},{"l":66},{"l":66},{"l":66},{"l":66}],"midgroundLayer":{"213":[{"g":200682,"x":258,"y":290.5,"hue":[-39,-46,-71],"cw":86,"ch":56}],"216":[{"g":200681,"x":514,"y":273.5,"hue":[-39,-46,-71],"cw":94,"ch":77}],"228":[{"g":200682,"x":301,"y":312,"hue":[-39,-46,-71],"cw":86,"ch":56}],"230":[{"g":200681,"x":471,"y":295,"hue":[-39,-46,-71],"cw":94,"ch":77}],"242":[{"g":200682,"x":344,"y":333.5,"hue":[-39,-46,-71],"cw":86,"ch":56}],"243":[{"g":200681,"x":428,"y":316.5,"hue":[-39,-46,-71],"cw":94,"ch":77}],"257":[{"g":200681,"x":385,"y":338,"hue":[-39,-46,-71],"cw":94,"ch":77}],"263":[{"g":200681,"x":901,"y":338,"hue":[-39,-46,-71],"cw":94,"ch":77}],"270":[{"g":200681,"x":342,"y":359.5,"hue":[-39,-46,-71],"cw":94,"ch":77}],"271":[{"g":200682,"x":430,"y":376.5,"hue":[-39,-46,-71],"cw":86,"ch":56}],"276":[{"g":200681,"x":858,"y":360.5,"hue":[-39,-46,-71],"cw":94,"ch":77}],"284":[{"g":200681,"x":299,"y":381,"hue":[-39,-46,-71],"cw":94,"ch":77}],"290":[{"g":200681,"x":815,"y":381,"hue":[-39,-46,-71],"cw":94,"ch":77}],"303":[{"g":200681,"x":772,"y":402.5,"hue":[-39,-46,-71],"cw":94,"ch":77}],"304":[{"g":200682,"x":860,"y":419.5,"hue":[-39,-46,-71],"cw":86,"ch":56}],"317":[{"g":200681,"x":729,"y":424,"hue":[-39,-46,-71],"cw":94,"ch":77}],"318":[{"g":200681,"x":815,"y":424,"hue":[-39,-46,-71],"cw":94,"ch":77}],"319":[{"g":200682,"x":903,"y":441,"hue":[-39,-46,-71],"cw":86,"ch":56}],"330":[{"g":200681,"x":686,"y":445.5,"hue":[-39,-46,-71],"cw":94,"ch":77}],"331":[{"g":200681,"x":772,"y":445.5,"hue":[-39,-46,-71],"cw":94,"ch":77}],"333":[{"g":200682,"x":946,"y":462.5,"hue":[-39,-46,-71],"cw":86,"ch":56}],"337":[{"g":200682,"x":43,"y":484,"hue":[-39,-46,-71],"cw":86,"ch":56}],"345":[{"g":200681,"x":729,"y":467,"hue":[-39,-46,-71],"cw":94,"ch":77}],"348":[{"g":200682,"x":989,"y":484,"hue":[-39,-46,-71],"cw":86,"ch":56}],"351":[{"g":200682,"x":86,"y":505.5,"hue":[-39,-46,-71],"cw":86,"ch":56}],"362":[{"g":200682,"x":1032,"y":505.5,"hue":[-39,-46,-71],"cw":86,"ch":56}],"366":[{"g":200682,"x":129,"y":527,"hue":[-39,-46,-71],"cw":86,"ch":56}],"380":[{"g":200682,"x":172,"y":548.5,"hue":[-39,-46,-71],"cw":86,"ch":56}],"395":[{"g":200682,"x":215,"y":570,"hue":[-39,-46,-71],"cw":86,"ch":56}],"439":[{"g":200682,"x":430,"y":634.5,"hue":[-39,-46,-71],"cw":86,"ch":56}],"453":[{"g":200681,"x":385,"y":639,"hue":[-39,-46,-71],"cw":94,"ch":77}],"457":[{"g":200682,"x":731,"y":656,"hue":[-39,-46,-71],"cw":86,"ch":56}],"467":[{"g":200681,"x":428,"y":660.5,"hue":[-39,-46,-71],"cw":94,"ch":77}],"482":[{"g":200682,"x":473,"y":699,"hue":[-39,-46,-71],"cw":86,"ch":56}],"496":[{"g":200682,"x":516,"y":720.5,"hue":[-39,-46,-71],"cw":86,"ch":56}],"560":[{"g":200682,"x":559,"y":742,"hue":[-39,-46,-71],"cw":86,"ch":56}]},"atlasLayout":{"width":96,"height":137,"graphicsPositions":{"200681":{"sx":1,"sy":1,"sw":94,"sh":77},"200682":{"sx":1,"sy":80,"sw":86,"sh":56}}}}