{"id":136577030,"topNeighbourId":136577029,"bottomNeighbourId":136577031,"leftNeighbourId":136708614,"rightNeighbourId":136577542,"shadowBonusOnEntities":-1,"cells":[{"l":2},{"l":2},{"l":2},{"l":2},{"l":2},{"l":2},{"l":2},{"l":66},{"l":66},{"l":66},{"l":66},{"l":66},{"l":2},{"l":2},{"l":2},{"l":2},{"l":2},{"l":2},{"l":2},{"l":2},{"l":2},{"l":66},{"l":66},{"l":66},{"l":66},{"l":66},{"l":2},{"l":2},{"l":2},{"l":2},{"l":2},{"l":2},{"l":2},{"l":2},{"l":2},{"l":66},{"l":66},{"l":66},{"l":66},{"l":66},{"l":2},{"l":2},{"l":2},{"l":2},{"l":2},{"l":2},{"l":2},{"l":2},{"l":2},{"l":66},{"l":66},{"l":66},{"l":66},{"l":66},{"l":2},{"l":2},{"l":2},{"l":2},{"l":2},{"l":2},{"l":2},{"l":2},{"l":2},{"l":66},{"l":66},{"l":66},{"l":66},{"l":66},{"l":66},{"l":2},{"l":2},{"l":2},{"l":2},{"l":2},{"l":2},{"l":2},{"l":2},{"l":66},{"l":66},{"l":66},{"l":66},{"l":66},{"l":2},{"l":2},{"l":2},{"l":2},{"l":2},{"l":2},{"l":2},{"l":2},{"l":2},{"l":66},{"l":66},{"l":66},{"l":66},{"l":66},{"l":66},{"l":2},{"l":2},{"l":2},{"l":2},{"l":2},{"l":2},{"l":2},{"l":2},{"l":66},{"l":66},{"l":66},{"l":66},{"l":66},{"l":66},{"l":2},{"l":2},{"l":2},{"l":2},{"l":2},{"l":2},{"l":2},{"l":2},{"l":2},{"l":2},{"l":66},{"l":66},{"l":66},{"l":66},{"l":2},{"l":2},{"l":2},{"l":2},{"l":2},{"l":2},{"l":2},{"l":2},{"l":2},{"l":66},{"l":66},{"l":66},{"l":66},{"l":66},{"l":2},{"l":2},{"l":2},{"l":2},{"l":2},{"l":2},{"l":2},{"l":2},{},{"l":2},{"l":66},{"l":66},{"l":66},{"l":66},{"l":2},{"l":2},{"l":2},{"l":2},{"l":2},{"l":2},{"l":2},{},{},{"l":2},{"l":66},{"l":66},{"l":66},{"l":66},{"l":2},{"l":2},{"l":2},{"l":2},{"l":2},{"l":2},{"l":2},{},{"l":66},{},{"l":66},{"l":66},{"l":66},{"l":66},{"l":2},{"l":2},{"l":2},{"l":2},{"l":2},{"l":2},{},{"l":71},{"l":67},{},{"l":66},{"l":66},{"l":66},{"l":66},{"l":2},{"l":2},{"l":2},{"l":2},{"l":2},{"l":2},{"l":2},{"l":64},{"l":67},{"l":75},{},{"l":66},{"l":66},{"l":66},{"l":66},{"l":2},{"l":2},{"l":2},{},{"l":2},{},{"l":67},{"l":67},{},{"l":64},{"l":66},{"l":2},{"l":66},{"l":2},{"l":2},{"l":2},{"l":2},{},{"l":64},{},{"l":195},{"l":75},{"l":67},{"l":67},{"l":64},{"l":66},{"l":2},{"l":66},{"l":2},{"l":2},{},{"l":67},{"l":64},{"l":67},{"l":67},{"l":67},{"l":67},{"l":67},{"l":64},{"l":2},{"l":66},{"l":2},{"l":2},{"l":2},{},{"l":67},{"l":67},{"l":67},{"l":75},{"l":3},{"l":83},{"l":67},{"l":67},{},{"l":2},{"l":66},{"l":2},{"l":2},{"l":64},{"l":67},{"l":67},{"l":67},{"l":3},{"l":67},{"l":83},{"l":67},{},{},{"l":2},{"l":2},{"l":2},{"l":2},{},{"l":67},{"l":67},{"l":75},{"l":67},{"l":3},{"l":67},{"l":67},{},{},{},{"l":2},{"l":2},{},{"l":67},{"l":67},{"l":67},{"l":67},{},{"l":3},{"l":67},{"l":67},{},{"l":66},{},{"l":2},{"l":2},{"l":64},{"l":67},{"l":67},{"l":75},{"l":67},{},{},{"l":67},{"l":67},{"l":64},{"l":66},{"l":67},{},{},{"l":67},{"l":67},{"l":67},{"l":67},{"l":66},{},{"l":66},{"l":67},{"l":67},{"l":66},{"l":67},{"l":3},{},{},{"l":3},{"l":67},{"l":75},{"l":67},{"l":67},{"l":66},{"l":2},{"l":3},{"l":83},{"l":67},{"l":67},{"l":19},{"l":3},{"l":3},{"l":3},{"l":67},{"l":67},{"l":67},{"l":67},{"l":67},{"l":67},{"l":67},{"l":83},{"l":67},{"l":83},{"l":3},{},{},{"l":3},{"l":11},{"l":67},{"l":67},{"l":67},{"l":67},{"l":67},{},{"l":67},{"l":67},{"l":3},{"l":3},{},{},{"l":3},{"l":3},{"l":67},{"l":67},{"l":67},{"l":67},{"l":64},{"l":64},{"l":67},{"l":67},{"l":3},{},{"l":2},{"l":2},{},{"l":3},{"l":11},{"l":67},{"l":67},{"l":67},{"l":67},{"l":64},{"l":67},{"l":67},{"l":3},{},{"l":66},{"l":2},{},{"l":3},{"l":3},{"l":67},{"l":67},{"l":67},{"l":67},{"l":67},{"l":75},{"l":67},{},{"l":66},{"l":2},{"l":2},{"l":2},{},{"l":3},{"l":3},{"l":67},{"l":83},{"l":67},{"l":67},{"l":11},{"l":67},{"l":67},{"l":64},{"l":2},{"l":2},{"l":2},{},{"l":3},{"l":3},{"l":83},{"l":83},{"l":67},{"l":3},{"l":67},{"l":67},{"l":64},{"l":66},{"l":2},{"l":2},{"l":2},{"l":2},{},{"l":3},{"l":3},{"l":83},{"l":67},{"l":3},{"l":3},{"l":67},{"l":64},{"l":66},{"l":2},{"l":2},{"l":2},{"l":2},{},{"l":3},{"l":3},{"l":67},{"l":3},{"l":3},{"l":67},{"l":64},{"l":66},{"l":66},{"l":2},{"l":2},{"l":2},{"l":2},{"l":66},{},{"l":3},{"l":3},{"l":3},{"l":3},{},{"l":64},{"l":66},{"l":66},{"l":2},{"l":2},{"l":2},{"l":2},{"l":66},{},{"l":3},{"l":3},{"l":3},{},{"l":64},{"l":66},{"l":66},{"l":2},{"l":2},{"l":2},{"l":2},{"l":2},{"l":66},{"l":66},{},{"l":3},{"l":3},{},{"l":66},{"l":66},{"l":66},{"l":66},{"l":2},{"l":2},{"l":2},{"l":2},{"l":2},{"l":66},{},{"l":3},{},{"l":66},{"l":66},{"l":66},{"l":66},{"l":2},{"l":2},{"l":2},{"l":2},{"l":2},{"l":2},{"l":2},{"l":66},{},{},{"l":66},{"l":66},{"l":66},{"l":66},{"l":2},{"l":2},{"l":2},{"l":2},{"l":2},{"l":2},{"l":66},{"l":66},{},{"l":66},{"l":66},{"l":66},{"l":66},{"l":2},{"l":2},{"l":2}],"midgroundLayer":{"197":[{"g":50409,"x":28,"y":-27,"hue":[-10,-16,-37],"cw":202,"ch":379},{"g":50409,"x":28,"y":-283,"hue":[-10,-16,-37],"cw":202,"ch":379}],"218":[{"g":201392,"x":703,"y":284.5,"hue":[-2,-8,-49],"cw":57,"ch":55},{"g":3299,"x":781,"y":260.5,"hue":[-25,-31,-68],"sx":-1,"cw":49,"ch":81},{"g":48841,"x":745,"y":290.5,"hue":[-6,-22,-60],"sx":-1,"cw":59,"ch":61}],"222":[{"g":50417,"x":1098,"y":300.5,"hue":[11,3,-36],"sx":-1,"cw":142,"ch":187}],"224":[{"g":50409,"x":-58,"y":16,"hue":[-13,-18,-38],"cw":202,"ch":379},{"g":50409,"x":-58,"y":-240,"hue":[-13,-18,-38],"cw":202,"ch":379}],"227":[{"g":50444,"x":161,"y":3,"hue":[9,1,-28],"cw":180,"ch":410},{"g":50443,"x":143,"y":-9,"hue":[9,1,-28],"cw":210,"ch":432},{"g":55717,"x":249,"y":275,"hue":[37,10,-56],"sx":-1,"cw":29,"ch":17}],"228":[{"g":50450,"x":335,"y":-85,"hue":[2,-6,-37],"cy":-70,"cw":200,"ch":353},{"g":51834,"x":499,"y":252,"hue":[12,4,-27],"sx":-1,"cw":189,"ch":101},{"g":46086,"x":266,"y":131,"hue":[0,0,0],"cw":114,"ch":231}],"229":[{"g":50437,"x":473,"y":300,"hue":[-13,-22,-53],"sx":-1,"cw":86,"ch":71},{"g":46087,"x":492,"y":49,"hue":[-1,-13,-44],"sx":-1,"cw":123,"ch":231}],"233":[{"g":48841,"x":745,"y":288,"hue":[-6,-22,-60],"cw":59,"ch":61}],"237":[{"g":46084,"x":1213,"y":140,"hue":[-60,-60,-60],"sx":-1,"cw":183,"ch":236}],"238":[{"g":56000,"x":-105,"y":82.5,"hue":[0,0,0],"cw":217,"ch":274}],"252":[{"g":50409,"x":-144,"y":-197,"hue":[-19,-23,-42],"cw":202,"ch":379}],"254":[{"g":57223,"x":76,"y":169,"hue":[12,-10,-68],"cw":173,"ch":88}],"255":[{"g":57223,"x":190,"y":106,"hue":[12,-10,-68],"cw":173,"ch":88}],"267":[{"g":56000,"x":27,"y":-188.5,"hue":[0,0,0],"cw":217,"ch":274}],"276":[{"g":39405,"x":927,"y":376.5,"hue":[-24,-28,-60],"sx":-1,"cw":60,"ch":52}],"280":[{"g":50448,"x":17,"y":40,"hue":[-24,-31,-53],"cw":208,"ch":429}],"290":[{"g":63177,"x":816,"y":405,"hue":[-18,-27,-72],"cw":61,"ch":41}],"291":[{"g":201259,"x":900,"y":359,"hue":[-25,-31,-70],"cw":69,"ch":88},{"g":702269,"x":996,"y":417,"hue":[-5,-10,-41],"sx":-1,"cw":71,"ch":46}],"294":[{"g":51834,"x":190,"y":374.5,"hue":[-3,-10,-34],"sx":-1,"cw":189,"ch":101}],"300":[{"g":50455,"x":531,"y":425.5,"hue":[-17,-25,-62],"cw":68,"ch":47},{"g":50455,"x":528,"y":404.5,"hue":[-2,-10,-47],"cw":68,"ch":47}],"308":[{"g":50408,"x":-163,"y":32,"hue":[-17,-22,-41],"cx":-110,"cw":115,"ch":495}],"314":[{"g":50455,"x":488,"y":447,"hue":[-24,-33,-69],"cw":68,"ch":47}],"315":[{"g":50458,"x":558,"y":408,"hue":[-6,-14,-51],"cw":110,"ch":98},{"g":50459,"x":563,"y":376,"hue":[0,-8,-45],"cw":72,"ch":83},{"g":38215,"x":584,"y":365,"hue":[17,9,-28],"cw":40,"ch":34}],"318":[{"g":36919,"x":963,"y":410,"hue":[-15,-22,-57],"sx":-1,"cw":97,"ch":63},{"g":63178,"x":846,"y":433,"hue":[-15,-24,-66],"cw":66,"ch":56},{"g":48839,"x":858,"y":391,"hue":[-6,-22,-60],"cw":147,"ch":95}],"327":[{"g":50457,"x":459,"y":477.5,"hue":[-2,-10,-46],"cw":50,"ch":36},{"look":2000,"x":469,"y":482.5,"hue":[18,10,-26],"dmin":3,"dmax":8,"anim":1,"astc":1}],"328":[{"g":50458,"x":603,"y":429.5,"hue":[-10,-21,-65],"sx":-1,"cw":110,"ch":98},{"g":50455,"x":537,"y":429.5,"hue":[-10,-18,-56],"cw":68,"ch":47},{"g":48836,"x":515,"y":452.5,"hue":[-6,-22,-60],"cw":121,"ch":62}],"332":[{"g":29507,"x":892,"y":480.5,"hue":[-11,-21,-55],"cw":34,"ch":22}],"343":[{"g":50456,"x":574,"y":490,"hue":[-17,-29,-72],"cw":63,"ch":48}],"350":[{"g":50416,"x":-10,"y":396.5,"hue":[-29,-33,-55],"sx":-1,"cw":135,"ch":173}],"363":[{"g":50415,"x":1235,"y":371.5,"hue":[2,-2,-31],"sx":-1,"cw":157,"ch":165}],"372":[{"g":50427,"x":650,"y":473,"hue":[15,7,-32],"cw":94,"ch":116}],"377":[{"g":50416,"x":1068,"y":422,"hue":[-6,-11,-41],"cw":135,"ch":173}],"378":[{"g":50416,"x":85,"y":444.5,"hue":[-26,-31,-55],"sx":-1,"cw":135,"ch":173}],"385":[{"g":48839,"x":614,"y":525.5,"hue":[-24,-38,-70],"cw":147,"ch":95}],"404":[{"g":50415,"x":930,"y":479,"hue":[-3,-8,-40],"cw":157,"ch":165}],"422":[{"g":50416,"x":203,"y":504,"hue":[-26,-31,-56],"sx":-1,"cw":135,"ch":173}],"434":[{"g":38717,"x":-115,"y":549.5,"hue":[-29,-31,-50],"cx":-62,"cw":137,"ch":216}],"465":[{"g":50416,"x":320,"y":562.5,"hue":[-31,-35,-60],"sx":-1,"cw":135,"ch":173}],"494":[{"g":50416,"x":438,"y":621.5,"hue":[-31,-35,-60],"sx":-1,"cw":135,"ch":173}],"498":[{"g":50417,"x":667,"y":609.5,"hue":[-19,-23,-52],"cw":142,"ch":187}],"504":[{"g":45595,"x":56,"y":554,"hue":[-32,-34,-50],"sx":-1,"cw":116,"ch":297}],"560":[{"g":50416,"x":550,"y":681,"hue":[-31,-35,-60],"cw":135,"ch":173},{"g":45595,"x":185,"y":618.5,"hue":[-30,-33,-50],"sx":-1,"cw":116,"ch":297},{"g":50415,"x":577,"y":679.5,"hue":[-36,-39,-61],"sx":-1,"cw":157,"ch":165},{"g":202697,"x":567,"y":825.5,"hue":[-24,-29,-49],"sx":-1,"cw":75,"ch":25},{"g":48841,"x":546,"y":795.5,"hue":[-55,-65,-85],"sx":-1,"cw":59,"ch":61},{"g":48841,"x":546,"y":795.5,"hue":[-55,-65,-85],"sx":-1,"cw":59,"ch":61},{"g":57968,"x":389,"y":454.5,"hue":[-128,-128,-128],"sx":-1,"cw":442,"ch":396},{"g":48837,"x":-56.5,"y":42,"hue":[-88,-88,-98],"cx":-3.5,"cy":54,"cw":66,"ch":108},{"g":54195,"x":155,"y":807.5,"hue":[-39,-46,-68],"sx":-0.692,"sy":0.692,"cx":426,"cy":263.5,"cw":727,"ch":326},{"g":55998,"x":18.5,"y":842.5,"hue":[0,0,0],"sx":-1,"alpha":0.6431372549019608,"cx":82.5,"cy":78.5,"cw":165,"ch":157},{"g":47379,"x":587,"y":412,"hue":[0,0,0],"cx":640,"cy":427,"cw":1267,"ch":866},{"g":56004,"x":198,"y":822.5,"hue":[0,0,0],"sx":-0.882,"sy":0.882,"alpha":0.5686274509803921,"cx":46,"cy":103.5,"cw":92,"ch":195},{"g":55999,"x":197,"y":693,"hue":[0,0,0],"sx":-1,"alpha":0.44313725490196076,"cx":59,"cy":51,"cw":118,"ch":102},{"g":55998,"x":-33.5,"y":641.5,"hue":[0,0,0],"sx":-1,"alpha":0.6431372549019608,"cx":82.5,"cy":78.5,"cw":165,"ch":157},{"g":56002,"x":1124,"y":652.5,"hue":[0,0,0],"alpha":0.41568627450980394,"cx":32,"cy":52.5,"cw":64,"ch":105},{"g":56004,"x":1191,"y":759.5,"hue":[0,0,0],"alpha":0.4980392156862745,"cx":46,"cy":103.5,"cw":92,"ch":195},{"g":56002,"x":1183,"y":99.5,"hue":[0,0,0],"alpha":0.41568627450980394,"cx":32,"cy":52.5,"cw":64,"ch":105},{"g":55998,"x":46.5,"y":826.5,"hue":[0,0,0],"sx":-1,"alpha":0.6431372549019608,"cx":82.5,"cy":78.5,"cw":165,"ch":157},{"g":55998,"x":254.5,"y":841.5,"hue":[0,0,0],"sx":-1,"alpha":0.6431372549019608,"cx":82.5,"cy":78.5,"cw":165,"ch":157},{"g":55998,"x":329.5,"y":819.5,"hue":[0,0,0],"sx":-1,"alpha":0.6431372549019608,"cx":82.5,"cy":78.5,"cw":165,"ch":157}]},"atlasLayout":{"width":1463,"height":842,"graphicsPositions":{"3299":{"sx":385,"sy":727,"sw":49,"sh":81},"29507":{"sx":1115,"sy":357,"sw":34,"sh":22},"36919":{"sx":1049,"sy":737,"sw":97,"sh":63},"38215":{"sx":1074,"sy":802,"sw":40,"sh":34},"38717":{"sx":657,"sy":760,"sw":49,"sh":78,"cx":62,"cw":137,"ch":216},"39405":{"sx":495,"sy":763,"sw":60,"sh":52},"45595":{"sx":844,"sy":176,"sw":21,"sh":55,"cw":116,"ch":297},"46084":{"sx":730,"sy":176,"sw":112,"sh":145,"cw":183,"ch":236},"46086":{"sx":1368,"sy":257,"sw":67,"sh":136,"cw":114,"ch":231},"46087":{"sx":1368,"sy":119,"sw":73,"sh":136,"cw":123,"ch":231},"47379":{"sx":1251,"sy":498,"sw":190,"sh":130,"cx":21,"cy":37,"cw":1267,"ch":866},"48836":{"sx":262,"sy":727,"sw":121,"sh":62},"48837":{"sx":1251,"sy":733,"sw":66,"sh":108,"cx":73},"48839":{"sx":1,"sy":727,"sw":147,"sh":95},"48841":{"sx":776,"sy":760,"sw":59,"sh":61},"50408":{"sx":1251,"sy":1,"sw":115,"sh":495,"cx":110},"50409":{"sx":867,"sy":1,"sw":202,"sh":379},"50415":{"sx":1071,"sy":190,"sw":157,"sh":165},"50416":{"sx":730,"sy":1,"sw":135,"sh":173},"50417":{"sx":1071,"sy":1,"sw":142,"sh":187},"50427":{"sx":1368,"sy":1,"sw":94,"sh":116},"50437":{"sx":1148,"sy":737,"sw":86,"sh":71},"50443":{"sx":445,"sy":329,"sw":210,"sh":432},"50444":{"sx":867,"sy":382,"sw":180,"sh":410},"50448":{"sx":657,"sy":329,"sw":208,"sh":429},"50450":{"sx":1049,"sy":382,"sw":200,"sh":353,"cy":70},"50455":{"sx":837,"sy":794,"sw":68,"sh":47},"50456":{"sx":557,"sy":763,"sw":63,"sh":48},"50457":{"sx":1022,"sy":802,"sw":50,"sh":36},"50458":{"sx":150,"sy":727,"sw":110,"sh":98},"50459":{"sx":1390,"sy":733,"sw":72,"sh":83},"51834":{"sx":1251,"sy":630,"sw":189,"sh":101},"54195":{"sx":1,"sy":1,"sw":727,"sh":326},"55717":{"sx":622,"sy":763,"sw":29,"sh":17},"55998":{"sx":970,"sy":794,"sw":50,"sh":47,"cw":165,"ch":157},"55999":{"sx":335,"sy":791,"sw":42,"sh":36,"cw":118,"ch":102},"56000":{"sx":1368,"sy":395,"sw":73,"sh":92,"cw":217,"ch":274},"56002":{"sx":837,"sy":760,"sw":18,"sh":30,"cw":64,"ch":105},"56004":{"sx":1215,"sy":1,"sw":29,"sh":60,"cw":92,"ch":195},"57223":{"sx":1071,"sy":357,"sw":42,"sh":21,"cw":173,"ch":88},"57968":{"sx":1,"sy":329,"sw":442,"sh":396},"63177":{"sx":907,"sy":794,"sw":61,"sh":41},"63178":{"sx":708,"sy":760,"sw":66,"sh":56},"201259":{"sx":1319,"sy":733,"sw":69,"sh":88},"201392":{"sx":436,"sy":763,"sw":57,"sh":55},"202697":{"sx":557,"sy":813,"sw":75,"sh":25},"702269":{"sx":262,"sy":791,"sw":71,"sh":46}}}}