{"id":136578050,"topNeighbourId":136578049,"bottomNeighbourId":136578051,"leftNeighbourId":136577538,"rightNeighbourId":136578562,"shadowBonusOnEntities":-1,"cells":[{"l":2},{"l":2},{"l":2},{"l":2},{"l":2},{"l":2},{"l":2},{"l":2},{"l":2},{"l":2},{"l":2},{},{"l":67},{"l":3},{"l":2},{"l":2},{"l":2},{"l":2},{"l":2},{"l":2},{"l":2},{"l":2},{"l":2},{"l":2},{},{"l":67},{"l":67},{"l":3},{"l":2},{"l":2},{"l":2},{"l":2},{"l":2},{"l":2},{"l":2},{"l":2},{"l":2},{"l":2},{},{},{"l":67},{"l":67},{"l":2},{"l":2},{"l":2},{"l":2},{"l":2},{"l":2},{"l":2},{"l":2},{"l":2},{},{},{"l":67},{"l":67},{"l":3},{"l":2},{"l":2},{"l":2},{"l":2},{"l":66},{"l":2},{"l":2},{"l":2},{"l":2},{},{"l":66},{"l":67},{"l":3},{"l":67},{"l":2},{"l":2},{"l":2},{"l":66},{"l":66},{"l":2},{"l":2},{"l":2},{},{"l":2},{"l":67},{"l":3},{"l":3},{"l":67},{"l":2},{"l":2},{"l":2},{"l":2},{"l":66},{"l":66},{"l":2},{"l":2},{},{"l":66},{"l":67},{"l":67},{},{"l":67},{"l":2},{"l":2},{"l":2},{"l":66},{"l":66},{"l":66},{"l":2},{},{"l":67},{"l":67},{"l":67},{},{},{"l":67},{"l":2},{"l":2},{"l":2},{"l":2},{"l":66},{"l":2},{"l":2},{},{"l":67},{"l":67},{"l":67},{"l":67},{"l":67},{"l":67},{"l":2},{"l":2},{"l":2},{"l":66},{"l":66},{"l":2},{},{},{"l":67},{"l":3},{"l":67},{"l":67},{"l":67},{"l":67},{"l":2},{"l":2},{"l":2},{"l":2},{"l":66},{"l":2},{},{},{"l":67},{"l":3},{"l":3},{"l":83},{"l":67},{"l":67},{"l":2},{"l":2},{"l":2},{"l":2},{"l":66},{},{},{},{"l":67},{},{"l":67},{"l":83},{"l":67},{"l":67},{"l":2},{"l":2},{"l":2},{"l":66},{"l":66},{"l":64},{"l":67},{},{"l":67},{},{"l":67},{"l":67},{"l":83},{"l":67},{"l":2},{"l":2},{"l":2},{"l":2},{"l":64},{"l":67},{"l":67},{"l":67},{"l":67},{"l":67},{"l":67},{"l":67},{"l":83},{"l":67},{"l":2},{"l":2},{"l":2},{"l":2},{"l":64},{"l":67},{"l":83},{"l":67},{"l":67},{"l":67},{"l":67},{"l":67},{"l":67},{"l":67},{"l":2},{"l":2},{"l":2},{},{"l":67},{"l":67},{"l":67},{"l":67},{"l":67},{"l":83},{"l":67},{"l":67},{"l":67},{"l":67},{"l":2},{"l":2},{"l":2},{},{"l":195},{"l":83},{"l":67},{"l":67},{"l":67},{"l":67},{"l":83},{"l":67},{"l":67},{"l":67},{"l":2},{"l":2},{},{"l":67},{"l":67},{"l":67},{"l":67},{"l":2},{"l":67},{"l":67},{"l":67},{"l":2},{"l":67},{"l":67},{"l":2},{"l":2},{},{"l":2},{"l":67},{"l":67},{"l":67},{"l":67},{"l":2},{"l":67},{"l":67},{"l":2},{},{"l":67},{"l":2},{},{"l":66},{"l":67},{"l":67},{"l":67},{"l":75},{"l":67},{"l":2},{"l":67},{"l":67},{},{"l":66},{"l":67},{"l":2},{},{"l":66},{"l":67},{"l":67},{"l":67},{"l":67},{"l":67},{"l":67},{"l":2},{"l":67},{"l":66},{"l":66},{"l":67},{"l":2},{},{"l":67},{"l":3},{"l":67},{"l":2},{"l":67},{"l":83},{"l":67},{"l":2},{"l":67},{"l":67},{"l":67},{"l":67},{"l":2},{},{"l":67},{"l":3},{"l":67},{"l":67},{"l":2},{"l":67},{"l":83},{"l":67},{"l":2},{"l":67},{"l":67},{"l":3},{},{"l":66},{"l":3},{"l":3},{"l":67},{"l":67},{"l":2},{"l":67},{"l":67},{"l":67},{"l":66},{"l":67},{"l":67},{"l":3},{},{"l":66},{"l":67},{},{"l":67},{"l":67},{"l":67},{"l":2},{"l":67},{"l":75},{"l":67},{"l":67},{"l":67},{"l":3},{"l":67},{"l":67},{},{"l":67},{"l":67},{"l":67},{"l":67},{"l":2},{"l":67},{"l":67},{"l":67},{"l":67},{"l":3},{"l":3},{"l":3},{"l":67},{"l":67},{"l":67},{"l":67},{"l":67},{"l":67},{"l":67},{"l":2},{"l":67},{"l":67},{"l":67},{"l":3},{"l":3},{"l":67},{"l":67},{"l":67},{"l":67},{"l":75},{"l":67},{"l":67},{"l":67},{"l":66},{"l":67},{"l":3},{"l":11},{"l":67},{"l":3},{"l":3},{"l":67},{"l":67},{"l":67},{"l":67},{"l":67},{"l":67},{"l":67},{"l":67},{"l":67},{"l":67},{"l":3},{"l":3},{"l":3},{"l":3},{"l":67},{"l":67},{"l":67},{"l":67},{"l":75},{"l":67},{"l":67},{"l":67},{"l":67},{"l":11},{"l":67},{"l":3},{},{},{"l":67},{"l":67},{"l":67},{"l":67},{"l":67},{"l":67},{"l":67},{"l":67},{"l":67},{"l":3},{"l":3},{"l":3},{},{"l":3},{"l":67},{"l":75},{"l":67},{"l":75},{"l":67},{"l":75},{"l":67},{"l":67},{"l":3},{"l":3},{"l":3},{},{"l":2},{"l":3},{"l":67},{"l":67},{"l":67},{"l":67},{"l":67},{"l":67},{"l":67},{"l":3},{"l":3},{"l":67},{"l":3},{},{"l":2},{"l":3},{"l":67},{"l":67},{"l":67},{"l":67},{"l":67},{"l":67},{"l":67},{"l":3},{"l":3},{"l":3},{},{"l":2},{"l":2},{"l":3},{"l":3},{"l":67},{"l":67},{"l":67},{"l":67},{"l":67},{"l":67},{"l":3},{"l":3},{"l":3},{},{"l":2},{"l":2},{"l":3},{"l":3},{"l":67},{"l":67},{"l":75},{"l":67},{"l":67},{"l":3},{"l":3},{"l":3},{},{"l":2},{"l":2},{"l":2},{"l":3},{"l":3},{"l":67},{"l":67},{"l":67},{"l":67},{"l":67},{"l":3},{"l":3},{"l":3},{},{"l":2},{"l":2},{"l":2},{"l":3},{"l":3},{"l":67},{"l":67},{"l":67},{"l":3},{"l":3},{"l":67},{"l":3},{},{"l":2},{"l":2},{"l":2},{"l":2},{"l":3},{"l":3},{"l":3},{"l":67},{"l":67},{"l":67},{"l":3},{"l":3},{"l":3},{},{"l":2},{"l":2},{"l":2},{"l":2},{"l":3},{"l":3},{"l":3},{"l":67},{"l":67},{"l":3},{"l":3},{"l":3},{},{"l":2},{"l":2},{"l":2},{"l":2},{"l":2}],"midgroundLayer":{"17":[{"g":50414,"x":242,"y":-238.5,"hue":[-37,-42,-64],"cy":-159,"cw":270,"ch":192}],"52":[{"g":50413,"x":702,"y":-255.5,"hue":[-4,-9,-44],"cw":240,"ch":392},{"g":36243,"x":871,"y":1.5,"hue":[-44,-49,-84],"cw":118,"ch":76}],"61":[{"g":50414,"x":371,"y":-174,"hue":[-50,-57,-89],"cy":-159,"cw":270,"ch":192}],"76":[{"g":57968,"x":667,"y":-171.5,"hue":[-128,-128,-128],"sx":-1,"cy":-156,"cw":720,"ch":523}],"79":[{"g":61705,"x":772,"y":61.5,"hue":[-31,-36,-71],"cw":84,"ch":60}],"93":[{"g":50452,"x":736,"y":-39,"hue":[22,18,-15],"cw":65,"ch":94},{"g":46088,"x":829,"y":-8,"hue":[-39,-55,-81],"sx":-1,"cw":69,"ch":131}],"99":[{"g":49650,"x":-56,"y":-115.5,"hue":[-81,-85,-109],"cw":262,"ch":136}],"102":[{"g":49650,"x":202,"y":-115.5,"hue":[-76,-83,-118],"cw":262,"ch":136}],"106":[{"g":50413,"x":530,"y":-169.5,"hue":[9,6,-25],"cw":240,"ch":392}],"109":[{"g":50423,"x":946,"y":41.5,"hue":[7,1,-37],"cw":133,"ch":135},{"g":48833,"x":936,"y":97.5,"hue":[7,1,-37],"cw":140,"ch":94}],"110":[{"g":32820,"x":1043,"y":98.5,"hue":[21,16,-19],"cw":68,"ch":72},{"look":1999,"x":1075,"y":120.5,"hue":[0,0,0],"dmin":3,"dmax":8,"anim":1,"astc":1,"sx":-1}],"118":[{"g":61708,"x":487,"y":74,"hue":[-9,-17,-56],"cw":60,"ch":118},{"g":49717,"x":553,"y":-140,"hue":[-49,-57,-96],"sx":-1,"cy":-125,"cw":134,"ch":228}],"119":[{"g":46087,"x":680,"y":-51,"hue":[0,0,0],"sx":-1,"cy":-36,"cw":123,"ch":195}],"131":[{"g":48980,"x":521,"y":-278.5,"hue":[-60,-65,-88],"sx":-1,"cy":-263,"cw":100,"ch":156}],"140":[{"g":49650,"x":-185,"y":-51,"hue":[-85,-90,-111],"cw":262,"ch":136}],"143":[{"g":49650,"x":73,"y":-51,"hue":[-71,-78,-109],"cw":262,"ch":136}],"146":[{"g":50404,"x":557,"y":-67,"hue":[23,14,-26],"sx":-1,"cy":-52,"cw":139,"ch":272}],"147":[{"g":61706,"x":568,"y":165,"hue":[27,19,-23],"cw":102,"ch":75}],"149":[{"g":60352,"x":699,"y":-101,"hue":[70,66,-71],"cw":166,"ch":166}],"160":[{"g":61706,"x":525,"y":186.5,"hue":[0,-8,-51],"cw":102,"ch":75},{"g":59001,"x":537,"y":-8.5,"hue":[-10,18,-40],"cw":156,"ch":272}],"174":[{"g":46088,"x":479,"y":55,"hue":[31,25,-16],"cw":69,"ch":131}],"175":[{"g":48833,"x":558,"y":194,"hue":[3,-16,-94],"cw":140,"ch":94},{"g":32821,"x":577,"y":207,"hue":[2,-8,-50],"cw":53,"ch":67},{"g":38215,"x":630,"y":198,"hue":[0,0,0],"sx":-1,"cw":40,"ch":34}],"177":[{"g":50421,"x":731,"y":149,"hue":[10,3,-39],"cw":133,"ch":135},{"g":63183,"x":750,"y":172,"hue":[10,3,-39],"cw":43,"ch":61}],"183":[{"g":49650,"x":-56,"y":13.5,"hue":[-75,-80,-107],"cw":262,"ch":136}],"210":[{"g":49650,"x":-228,"y":56.5,"hue":[-80,-84,-113],"cw":262,"ch":136}],"227":[{"g":50403,"x":334,"y":61,"hue":[11,7,-23],"sx":-1,"cw":131,"ch":329}],"255":[{"g":36769,"x":234,"y":344,"hue":[-18,-23,-55],"cw":49,"ch":53},{"g":15529,"x":256,"y":372,"hue":[17,12,-20],"sx":-1,"cw":49,"ch":33}],"259":[{"g":50431,"x":618,"y":352,"hue":[28,22,-17],"cw":93,"ch":66}],"263":[{"g":36919,"x":915,"y":338,"hue":[-14,-20,-53],"cw":97,"ch":63}],"264":[{"g":36769,"x":992,"y":344,"hue":[-3,-9,-38],"cw":49,"ch":53}],"268":[{"g":50413,"x":14,"y":88.5,"hue":[11,6,-28],"cw":240,"ch":392}],"274":[{"g":50432,"x":680,"y":385.5,"hue":[21,15,-19],"cw":73,"ch":54}],"277":[{"g":35908,"x":970,"y":337.5,"hue":[-39,-45,-74],"cw":106,"ch":116}],"289":[{"g":50432,"x":723,"y":407,"hue":[17,11,-23],"cw":73,"ch":54}],"291":[{"g":32847,"x":925,"y":412,"hue":[-10,-17,-46],"cw":46,"ch":33}],"303":[{"g":50432,"x":766,"y":428.5,"hue":[12,7,-23],"cw":73,"ch":54}],"309":[{"g":36243,"x":54,"y":410,"hue":[-5,-10,-48],"cw":118,"ch":76},{"g":50452,"x":48,"y":305,"hue":[-5,-10,-48],"cw":65,"ch":94}],"313":[{"g":50431,"x":446,"y":438,"hue":[13,9,-22],"cw":93,"ch":66}],"322":[{"g":50392,"x":-120,"y":-327.5,"hue":[23,18,-17],"cw":855,"ch":604},{"g":50413,"x":-158,"y":174.5,"hue":[-12,-17,-54],"cw":240,"ch":392},{"g":35908,"x":24,"y":423.5,"hue":[-12,-17,-54],"cw":106,"ch":116},{"g":48969,"x":0,"y":252.5,"hue":[28,23,-14],"cw":77,"ch":238}],"328":[{"g":50432,"x":508,"y":471.5,"hue":[5,0,-27],"cw":73,"ch":54}],"331":[{"g":50433,"x":808,"y":449.5,"hue":[6,0,-26],"cw":94,"ch":66}],"336":[{"g":700648,"x":-46,"y":419,"hue":[-20,-29,-71],"cw":98,"ch":121}],"338":[{"g":12094,"x":138,"y":93,"hue":[30,25,-13],"sx":-1,"cw":30,"ch":51}],"343":[{"g":50432,"x":551,"y":493,"hue":[1,-3,-28],"cw":73,"ch":54}],"352":[{"g":50422,"x":172,"y":428.5,"hue":[6,1,-35],"cw":147,"ch":135}],"357":[{"g":50432,"x":594,"y":514.5,"hue":[-1,-6,-30],"cw":73,"ch":54}],"365":[{"g":60352,"x":11,"y":276,"hue":[70,66,-71],"cw":166,"ch":166}],"367":[{"g":46088,"x":276,"y":443,"hue":[0,0,0],"sx":-1,"cw":69,"ch":131}],"385":[{"g":50433,"x":636,"y":535.5,"hue":[-3,-8,-31],"cw":94,"ch":66}],"434":[{"g":50421,"x":-86,"y":557.5,"hue":[-12,-16,-45],"cw":133,"ch":135}],"435":[{"g":46084,"x":34,"y":-169.5,"hue":[0,0,0],"cy":-154,"cw":183,"ch":82}],"560":[{"g":50392,"x":370,"y":435.5,"hue":[-90,-90,-90],"cw":855,"ch":604},{"g":49650,"x":1163,"y":578.5,"hue":[-110,-110,-110],"cw":262,"ch":136},{"g":49650,"x":1034,"y":643.5,"hue":[-110,-110,-110],"cw":262,"ch":136},{"g":49650,"x":905,"y":707.5,"hue":[-110,-110,-110],"cw":262,"ch":136},{"g":49650,"x":1077,"y":750.5,"hue":[-110,-110,-110],"cw":262,"ch":136},{"g":49650,"x":776,"y":772.5,"hue":[-110,-110,-110],"cw":262,"ch":136},{"g":49650,"x":948,"y":815.5,"hue":[-108,-108,-109],"cw":262,"ch":136},{"g":49650,"x":647,"y":836.5,"hue":[-105,-106,-107],"cw":262,"ch":136},{"g":51832,"x":1040.5,"y":718,"hue":[-88,-91,-95],"cx":64.5,"cy":57,"cw":129,"ch":114},{"g":50423,"x":930.5,"y":753.5,"hue":[-88,-91,-95],"sx":1.665,"sy":1.665,"cx":66.5,"cy":67.5,"cw":133,"ch":135},{"g":28207,"x":562.5,"y":431,"hue":[0,0,0],"alpha":0.5647058823529412,"cx":615.5,"cy":446,"cw":1267,"ch":866}]},"atlasLayout":{"width":2009,"height":818,"graphicsPositions":{"12094":{"sx":412,"sy":607,"sw":30,"sh":51},"15529":{"sx":1955,"sy":296,"sw":49,"sh":33},"28207":{"sx":1263,"sy":526,"sw":221,"sh":151,"cx":37,"cy":53,"cw":1267,"ch":866},"32820":{"sx":97,"sy":727,"sw":68,"sh":72},"32821":{"sx":1955,"sy":164,"sw":53,"sh":67},"32847":{"sx":1351,"sy":775,"sw":46,"sh":33},"35908":{"sx":1,"sy":607,"sw":106,"sh":116},"36243":{"sx":1622,"sy":726,"sw":118,"sh":76},"36769":{"sx":1837,"sy":743,"sw":49,"sh":53},"36919":{"sx":171,"sy":607,"sw":97,"sh":63},"38215":{"sx":444,"sy":607,"sw":40,"sh":34},"46084":{"sx":1265,"sy":775,"sw":84,"sh":38,"cy":154,"cw":183,"ch":82},"46087":{"sx":1407,"sy":679,"sw":73,"sh":115,"cy":36,"cw":123,"ch":195},"46088":{"sx":231,"sy":672,"sw":35,"sh":67,"cw":69,"ch":131},"48833":{"sx":1265,"sy":679,"sw":140,"sh":94},"48969":{"sx":1955,"sy":1,"sw":52,"sh":161,"cw":77,"ch":238},"48980":{"sx":171,"sy":672,"sw":58,"sh":91,"cy":263,"cw":100,"ch":156},"49650":{"sx":999,"sy":526,"sw":262,"sh":136},"49717":{"sx":1486,"sy":589,"sw":134,"sh":228,"cy":125},"50392":{"sx":1,"sy":1,"sw":855,"sh":604},"50403":{"sx":1822,"sy":1,"sw":131,"sh":329},"50404":{"sx":858,"sy":526,"sw":139,"sh":272,"cy":52},"50413":{"sx":1580,"sy":1,"sw":240,"sh":392},"50414":{"sx":1580,"sy":395,"sw":270,"sh":192,"cy":159},"50421":{"sx":1771,"sy":606,"sw":133,"sh":135},"50422":{"sx":1622,"sy":589,"sw":147,"sh":135},"50423":{"sx":999,"sy":664,"sw":133,"sh":135},"50431":{"sx":1742,"sy":743,"sw":93,"sh":66},"50432":{"sx":337,"sy":607,"sw":73,"sh":54},"50433":{"sx":1,"sy":725,"sw":94,"sh":66},"50452":{"sx":270,"sy":607,"sw":65,"sh":94},"51832":{"sx":1134,"sy":679,"sw":129,"sh":114},"57968":{"sx":858,"sy":1,"sw":720,"sh":523,"cy":156},"59001":{"sx":1852,"sy":332,"sw":156,"sh":272},"60352":{"sx":1822,"sy":332,"sw":25,"sh":25,"cw":166,"ch":166},"61705":{"sx":1486,"sy":526,"sw":84,"sh":60},"61706":{"sx":1906,"sy":729,"sw":102,"sh":75},"61708":{"sx":109,"sy":607,"sw":60,"sh":118},"63183":{"sx":1955,"sy":233,"sw":43,"sh":61},"700648":{"sx":1906,"sy":606,"sw":98,"sh":121}}}}