{"id":137887747,"topNeighbourId":137887746,"bottomNeighbourId":137887748,"leftNeighbourId":138019331,"rightNeighbourId":137888259,"shadowBonusOnEntities":-1,"cells":[{"l":7},{"l":3},{"l":3},{"l":3,"c":-128},{"l":67,"c":-32},{"l":67,"c":-32},{"l":67,"c":-32},{"l":3,"c":-32},{"l":5,"c":32},{"l":2},{"l":2},{"l":2},{"l":2},{"l":2},{"l":3},{"l":3},{"l":3},{"l":3,"c":64},{"l":67,"c":64},{"l":67,"c":64},{"l":3,"c":64},{"l":3,"c":64},{},{"l":2},{"l":2},{"l":2},{"l":2},{"l":2},{"l":3},{"l":3},{"l":3},{"l":3},{"l":67},{"l":67},{"l":67},{"l":3},{"l":3},{},{"l":2},{"l":2},{"l":2},{"l":2},{"l":3},{"l":3},{"l":67},{"l":3},{"l":67},{"l":67},{"l":3},{"l":3},{},{"l":2},{"l":2},{"l":2},{"l":2},{"l":2},{"l":3},{"l":3},{"l":3},{"l":67},{"l":67},{"l":67},{"l":67},{"l":3},{"l":3},{},{"l":2},{"l":2},{"l":2},{"l":2},{"l":3},{"l":3},{"l":67},{"l":67},{"l":67},{"l":67},{"l":3},{"l":3},{},{"l":2},{"l":2},{"l":2},{"l":2},{"l":2},{"l":3},{"l":3},{"l":67},{"l":67},{"l":67},{"l":67},{"l":67},{"l":3},{"l":3},{},{"l":2},{"l":2},{"l":2},{"l":2},{"l":3},{"l":3},{"l":67},{"l":67},{"l":67},{"l":67},{"l":3},{"l":3},{},{"l":2},{"l":2},{"l":2},{"l":2},{"l":2},{"l":3},{"l":3},{"l":67},{"l":67},{"l":67},{"l":67},{"l":67},{"l":3},{"l":3},{},{"l":2},{"l":2},{"l":2},{"l":2},{"l":3},{"l":67},{"l":67},{"l":67},{"l":67},{"l":67},{"l":3},{"l":3},{},{"l":2},{"l":2},{"l":2},{"l":2},{"l":2},{"l":3},{"l":3},{"l":67},{"l":67},{"l":67},{"l":67},{"l":67},{"l":3},{},{"l":2},{"l":2},{"l":2},{"l":2},{"l":2},{"l":3},{"l":67},{"l":67},{"l":67},{"l":67},{"l":67},{"l":3},{},{"l":2},{"l":2},{"l":2},{"l":2},{"l":2},{"l":2},{"l":3},{"l":3},{"l":67},{"l":67},{"l":67},{"l":67},{"l":3},{},{"l":2},{"l":2},{"l":2},{"l":2},{"l":2},{"l":2},{"l":3},{"l":67},{"l":67},{"l":67},{"l":67},{"l":67},{},{"l":2},{"l":2},{"l":2},{"l":2},{"l":2},{"l":2},{"l":2},{"l":3},{"l":3},{"l":67},{"l":67},{"l":67},{"l":67},{"l":64},{"l":2},{"l":2},{"l":2},{"l":2},{"l":2},{"l":2},{"l":2},{"l":3},{"l":67},{"l":67},{"l":67},{"l":67},{"l":64},{"l":2},{"l":2},{"l":2},{"l":2},{"l":2},{"l":2},{"l":2},{"l":2},{"l":3},{"l":3},{"l":67},{"l":67},{"l":67},{"l":64},{"l":2},{"l":2},{"l":2},{"l":2},{"l":2},{"l":2},{"l":2},{"l":2},{"l":3},{"l":3},{"l":67},{"l":67},{"l":67},{},{"l":2},{"l":2},{"l":2},{"l":2},{"l":2},{"l":2},{"l":2},{"l":2},{},{"l":3},{"l":3},{"l":67},{"l":67},{"l":67},{},{"l":2},{"l":2},{"l":2},{"l":2},{"l":2},{"l":2},{"l":2},{},{"l":3},{"l":3},{"l":67},{"l":67},{},{"l":64},{"l":2},{"l":2},{"l":2},{"l":2},{"l":2},{"l":2},{"l":2},{"l":2},{},{"l":3},{"l":67},{"l":67},{"l":67},{"l":67},{"l":64},{"l":2},{"l":2},{"l":2},{"l":2},{"l":2},{"l":2},{"l":2},{},{"l":3},{"l":67},{"l":67},{"l":67},{"l":67},{"l":69},{"l":2},{"l":2},{"l":2},{"l":2},{"l":2},{"l":2},{"l":2},{"l":2},{},{"l":67},{"l":67},{"l":67},{"l":67},{"l":67},{},{"l":2},{"l":2},{},{},{},{"l":2},{},{"l":3},{"l":67},{"l":67},{"l":67},{"l":67},{"l":67},{},{"l":2},{},{},{},{"l":64},{"l":2},{},{"l":3},{"l":67},{"l":67},{"l":67},{"l":67},{"l":67},{"l":67},{"l":64},{"l":64},{"l":67},{},{"l":67},{},{"l":3},{"l":3},{"l":67},{"l":67},{"l":67},{"l":67},{"l":67},{"l":67},{"l":64},{"l":67},{"l":67},{"l":67},{"l":67,"c":-125},{},{"l":3},{"l":3},{"l":67},{"l":67},{"l":67},{"l":67},{"l":67},{"l":67},{"l":64},{"l":67},{"l":67},{"l":67},{"l":67,"c":1},{"l":3},{"l":3},{"l":3},{"l":67},{"l":67},{"l":67},{"l":67},{"l":67},{"l":67},{"l":67},{"l":67},{"l":67},{"l":67},{"l":3,"c":-125},{"l":3},{"l":3},{"l":3},{"l":67},{"l":67},{"l":67},{"l":67},{"l":67},{"l":67},{"l":67},{"l":67},{"l":67},{"l":67},{"l":67,"c":1},{"l":3},{"l":3},{"l":3},{"l":3},{"l":67},{"l":67},{"l":67},{"l":67},{"l":67},{"l":67},{"l":67},{"l":67},{"l":67},{"l":3,"c":-125},{"l":2},{"l":3},{"l":3},{"l":3},{"l":3},{"l":67},{"l":67},{"l":67},{"l":67},{"l":67},{"l":67},{"l":67},{"l":67},{"l":3,"c":1},{"l":2},{"l":3},{"l":3},{"l":3},{"l":3},{"l":67},{"l":67},{"l":67},{"l":67},{"l":67},{"l":67},{"l":67},{"l":3},{"l":3,"c":-125},{"l":2},{"l":2},{"l":3},{"l":3},{"l":3},{"l":67},{"l":67},{"l":67},{"l":67},{"l":67},{"l":67},{"l":67},{"l":67},{"l":3,"c":1},{"l":2},{"l":2},{"l":3},{"l":3},{"l":3},{"l":67},{"l":67},{"l":3},{"l":67},{"l":67},{"l":67},{"l":67},{"l":3},{"l":3,"c":-125},{"l":2},{"l":2},{"l":2},{"l":3},{"l":3},{"l":3},{"l":67},{"l":3},{"l":3},{"l":67},{"l":67},{"l":67},{"l":3},{"l":3},{"l":2},{"l":2},{"l":2},{"l":3},{"l":3},{"l":67},{"l":3},{"l":3},{"l":3},{"l":67},{"l":67},{"l":3},{"l":3},{"l":2},{"l":2},{"l":2},{"l":2},{"l":2},{"l":3},{"l":3},{"l":3},{"l":3},{"l":3},{"l":3},{"l":67},{"l":3},{"l":3},{"l":2},{"l":2},{"l":2},{"l":2},{"l":2},{"l":3},{"l":3},{"l":3},{"l":3},{"l":3},{"l":67},{"l":67},{"l":3},{"l":2},{"l":2},{"l":2},{"l":2},{"l":2},{"l":2},{"l":2},{"l":3},{"l":3},{"l":3},{"l":3},{"l":3},{"l":67},{"l":3},{"l":2},{"l":2},{"l":2},{"l":2},{"l":2},{"l":2},{"l":2},{"l":3},{"l":3},{"l":3},{"l":3},{"l":67},{"l":3},{"l":2},{"l":2},{"l":2}],"midgroundLayer":{"0":[{"g":202715,"x":-217,"y":-472,"hue":[-34,-36,-41],"cx":-164,"cy":-457,"cw":270,"ch":51},{"g":43136,"x":-156,"y":-85,"hue":[-24,-31,-64],"cx":-103,"cy":-70,"cw":1,"ch":44},{"g":9487,"x":-41,"y":-20,"hue":[0,0,0],"cy":-5,"cw":183,"ch":138}],"28":[{"g":202797,"x":-12,"y":-160,"hue":[-65,-67,-72],"cy":-141,"cw":206,"ch":118},{"g":202797,"x":-7,"y":-156,"hue":[-1,-5,-15],"cy":-141,"cw":206,"ch":118}],"40":[{"g":202722,"x":1035,"y":-567,"hue":[-44,-45,-54],"cw":384,"ch":709},{"g":203766,"x":896,"y":-701,"hue":[-32,-33,-41],"cy":-686,"cw":228,"ch":69}],"55":[],"56":[{"g":202192,"x":-159,"y":-17,"hue":[-39,-39,-40],"cx":-106,"cy":-2,"cw":132,"ch":193}],"98":[{"g":60356,"x":-160,"y":1.5,"hue":[12,-7,-44],"cw":361,"ch":142}],"180":[{"g":202682,"x":1259,"y":-35,"hue":[-25,-25,-25],"sx":-1,"cx":-45,"cy":-20,"cw":208,"ch":326}],"202":[{"g":202719,"x":525,"y":-267,"hue":[-47,-49,-58],"cy":-252,"cw":370,"ch":411},{"g":60356,"x":313,"y":152,"hue":[12,-7,-44],"cw":361,"ch":142},{"look":1076,"x":591,"y":271,"hue":[0,0,0],"sx":-1,"id":512897}],"215":[{"g":203040,"x":456,"y":284.5,"hue":[0,0,0],"cw":117,"ch":99}],"231":[{"g":700648,"x":537,"y":265,"hue":[-4,-10,-21],"cw":98,"ch":121}],"243":[{"look":685,"x":459,"y":380.5,"hue":[-1,-4,-25],"id":512659}],"250":[{"g":66463,"x":1052,"y":282.5,"hue":[0,0,0],"cw":44,"ch":92}],"251":[],"258":[{"g":34621,"x":502,"y":335,"hue":[-4,-10,-21],"cw":77,"ch":65}],"259":[{"g":203807,"x":1249,"y":-231,"hue":[-52,-54,-63],"sx":-1,"cx":-35,"cy":-216,"cw":703,"ch":529},{"g":203807,"x":1249,"y":-231,"hue":[-21,-25,-30],"sx":-1,"cx":-35,"cy":-216,"cw":703,"ch":529}],"271":[{"g":61005,"x":432,"y":353.5,"hue":[-1,-1,-11],"cw":89,"ch":74}],"279":[],"283":[{"g":50587,"x":768,"y":-726,"hue":[25,7,-24],"sx":-1,"cy":-711,"cw":821,"ch":515}],"287":[{"g":13430,"x":645,"y":306,"hue":[32,32,32],"sx":-1,"cw":53,"ch":125}],"288":[{"g":203895,"x":643,"y":327,"hue":[0,0,0],"id":512368,"cw":64,"ch":116}],"294":[{"g":202650,"x":-403,"y":-134.5,"hue":[-26,-29,-41],"cw":537,"ch":694}],"316":[{"g":201301,"x":720,"y":96,"hue":[0,0,0],"cw":46,"ch":38}],"321":[{"g":61892,"x":1076,"y":383,"hue":[-19,-21,-11],"cw":138,"ch":124},{"g":60356,"x":1001,"y":324,"hue":[12,-7,-44],"cw":361,"ch":142}],"330":[{"g":11337,"x":680,"y":424.5,"hue":[-11,-14,-15],"cw":96,"ch":83},{"g":60356,"x":528,"y":305.5,"hue":[12,-7,-44],"cw":361,"ch":142}],"332":[{"g":61312,"x":870,"y":362.5,"hue":[-32,-35,-47],"cw":49,"ch":163},{"look":1080,"x":968,"y":456.5,"hue":[4,7,-34],"sx":-1,"id":512901}],"333":[{"g":61894,"x":959,"y":442.5,"hue":[-19,-24,-27],"cw":83,"ch":71},{"look":2209,"x":1015,"y":446.5,"hue":[4,7,-34],"sx":-1,"id":512906}],"334":[{"look":1080,"x":1033,"y":484.5,"hue":[4,7,-34],"id":512908}],"345":[{"g":62804,"x":735,"y":480,"hue":[-19,-28,-67],"cw":47,"ch":35}],"348":[{"g":61005,"x":991,"y":461,"hue":[-26,-31,-46],"cw":89,"ch":74}],"361":[{"g":60356,"x":786,"y":388.5,"hue":[12,-7,-44],"cw":361,"ch":142}],"373":[{"g":43587,"x":849,"y":483,"hue":[-10,-10,-10],"sx":-1,"cw":117,"ch":99}],"560":[{"g":202650,"x":354,"y":306.5,"hue":[-39,-42,-51],"sx":-1,"cw":537,"ch":694},{"g":202721,"x":-98,"y":335.5,"hue":[-55,-59,-70],"cx":-45,"cw":360,"ch":515},{"g":60356,"x":55,"y":753.5,"hue":[12,-7,-44],"cw":361,"ch":142},{"g":60356,"x":571,"y":753.5,"hue":[12,-7,-44],"cw":361,"ch":142},{"g":60356,"x":12,"y":775.5,"hue":[12,-7,-44],"cw":361,"ch":142},{"g":202654,"x":1495,"y":551.5,"hue":[-44,-48,-54],"sx":-1,"cw":517,"ch":299},{"g":202654,"x":592,"y":615.5,"hue":[-57,-61,-74],"sx":-1,"cw":517,"ch":299},{"g":202674,"x":790,"y":715.5,"hue":[-39,-43,-49],"cw":424,"ch":135},{"g":202685,"x":1192,"y":695.5,"hue":[-42,-45,-55],"cw":22,"ch":155},{"g":202722,"x":433,"y":679.5,"hue":[-47,-50,-63],"cw":384,"ch":709}]},"atlasLayout":{"width":1122,"height":1779,"graphicsPositions":{"9487":{"sx":476,"sy":1605,"sw":27,"sh":21,"cy":5,"cw":183,"ch":138},"11337":{"sx":892,"sy":1677,"sw":96,"sh":83},"13430":{"sx":1068,"sy":877,"sw":53,"sh":125},"34621":{"sx":662,"sy":1713,"sw":77,"sh":65},"43136":{"sx":510,"sy":1605,"sw":1,"sh":7,"cx":103,"cy":70,"ch":44},"43587":{"sx":273,"sy":1666,"sw":117,"sh":99},"50587":{"sx":540,"sy":322,"sw":158,"sh":99,"cy":711,"cw":821,"ch":515},"60356":{"sx":427,"sy":1642,"sw":233,"sh":92,"cw":361,"ch":142},"61005":{"sx":427,"sy":1529,"sw":89,"sh":74},"61312":{"sx":1068,"sy":712,"sw":49,"sh":163},"61892":{"sx":540,"sy":196,"sw":138,"sh":124},"61894":{"sx":990,"sy":1677,"sw":83,"sh":71},"62804":{"sx":427,"sy":1605,"sw":47,"sh":35},"66463":{"sx":659,"sy":541,"sw":44,"sh":92},"201301":{"sx":540,"sy":647,"sw":46,"sh":38},"202192":{"sx":540,"sy":1,"sw":132,"sh":193,"cx":106,"cy":2},"202650":{"sx":1,"sy":1,"sw":537,"sh":694},"202654":{"sx":1,"sy":1228,"sw":517,"sh":299},"202674":{"sx":1,"sy":1529,"sw":424,"sh":135},"202682":{"sx":892,"sy":1229,"sw":208,"sh":326,"cx":45,"cy":20},"202685":{"sx":505,"sy":1605,"sw":3,"sh":23,"cw":22,"ch":155},"202715":{"sx":1,"sy":1666,"sw":270,"sh":51,"cx":164,"cy":457},"202719":{"sx":520,"sy":1229,"sw":370,"sh":411,"cy":252},"202721":{"sx":706,"sy":712,"sw":360,"sh":515,"cx":45},"202722":{"sx":706,"sy":1,"sw":384,"sh":709},"202797":{"sx":892,"sy":1557,"sw":206,"sh":118,"cy":141},"203040":{"sx":540,"sy":546,"sw":117,"sh":99},"203766":{"sx":662,"sy":1642,"sw":228,"sh":69,"cy":686},"203807":{"sx":1,"sy":697,"sw":703,"sh":529,"cx":35,"cy":216},"203895":{"sx":640,"sy":423,"sw":64,"sh":116},"700648":{"sx":540,"sy":423,"sw":98,"sh":121}}}}