{"id":141298694,"topNeighbourId":141298693,"bottomNeighbourId":141298695,"leftNeighbourId":141298182,"rightNeighbourId":141299206,"shadowBonusOnEntities":-1,"cells":[{"l":2},{"l":2},{"l":2},{"l":2},{"l":2},{"l":2},{"l":2},{"l":2},{"l":2},{"l":2},{"l":2},{"l":2},{"l":2},{"l":2},{"l":2},{"l":2},{"l":2},{"l":2},{"l":2},{"l":2},{"l":2},{"l":2},{"l":2},{"l":2},{"l":2},{"l":2},{"l":2},{"l":2},{"l":2},{"l":2},{"l":2},{"l":2},{"l":2},{"l":2},{"l":2},{"l":2},{"l":2},{"l":2},{"l":2},{"l":2},{"l":2},{"l":2},{"l":2},{"l":2},{"l":2},{"l":2},{"l":2},{"l":2},{"l":2},{"l":2},{"l":2},{"l":2},{"l":2},{"l":2},{"l":2},{"l":2},{"l":2},{"l":2},{"l":2},{"l":2},{"l":2},{"l":2},{"l":2},{"l":2},{"l":2},{"l":2},{"l":2},{"l":2},{"l":2},{"l":2},{"l":2},{"l":2},{"l":2},{"l":2},{"l":2},{"l":2},{"l":2},{"l":2},{"l":2},{"l":2},{"l":2},{"l":2},{"l":2},{"l":2},{"l":2},{"l":2},{"l":2},{"l":2},{"l":2},{"l":2},{"l":2},{"l":2},{"l":2},{"l":2},{"l":2},{"l":2},{"l":2},{"l":2},{"l":2},{"l":2},{"l":2},{"l":2},{"l":2},{"l":2},{"l":2},{"l":2},{"l":2},{"l":2},{"l":2},{"l":2},{"l":2},{"l":2},{"l":2},{"l":2},{"l":2},{"l":2},{"l":2},{"l":2},{"l":2},{"l":2},{"l":2},{"l":2},{"l":2},{"l":2},{"l":2},{"l":2},{"l":2},{"l":2},{"l":2},{"l":2},{"l":2},{"l":2},{"l":2},{"l":2},{"l":2},{"l":2},{"l":2},{"l":2},{"l":2},{"l":2},{"l":2},{"l":2},{"l":2},{"l":2},{"l":2},{"l":2},{"l":2},{"l":2},{"l":2},{"l":2},{"l":2},{"l":2},{"l":2},{"l":2},{"l":2},{"l":2},{"l":2},{"l":2},{"l":2},{"l":2},{"l":2},{"l":2},{"l":2},{"l":2},{"l":2},{"l":2},{"l":2},{"l":2},{"l":2},{"l":2},{"l":2},{"l":2},{"l":2},{"l":2},{"l":2},{"l":2},{"l":2},{"l":2},{"l":2},{"l":2},{"l":2},{"l":2},{"l":2},{"l":2},{"l":2},{"l":2},{"l":2},{"l":2},{"l":2},{"l":2},{"l":2},{"l":2},{"l":2},{"l":2},{"l":2},{"l":2},{"l":2},{"l":2},{"l":2},{"l":2},{"l":2},{"l":2},{"l":2},{},{"l":2},{"l":2},{"l":2},{"l":2},{"l":2},{"l":2},{"l":2},{"l":2},{"l":2},{"l":2},{"l":2},{"l":2},{},{},{"l":2},{"l":2},{"l":2},{"l":2},{"l":2},{"l":2},{"l":2},{"l":2},{"l":2},{"l":2},{"l":2},{"l":2},{"l":3},{"l":3},{"l":64},{"l":2},{"l":2},{"l":2},{"l":2},{"l":2},{"l":2},{"l":2},{"l":2},{"l":2},{"l":2},{"l":67},{"l":67},{"l":67},{},{"l":2},{"l":2},{"l":2},{"l":2},{"l":2},{"l":2},{"l":2},{"l":2},{"l":2},{"l":2},{},{"l":67},{"l":67},{"l":67},{},{"l":2},{"l":2},{"l":2},{"l":2},{"l":2},{"l":2},{"l":2},{"l":2},{},{"l":67},{"l":67},{"l":67},{"l":67},{},{"l":2},{"l":2},{"l":2},{"l":2},{"l":2},{"l":2},{"l":2},{"l":2},{"l":64},{"l":67},{"l":67},{"l":67},{"l":67},{"l":3},{},{"l":2},{"l":2},{"l":2},{"l":2},{"l":2},{"l":2},{"l":2},{"l":64},{"l":67},{"l":67},{"l":67},{"l":67},{"l":64},{"l":2},{"l":2},{"l":2},{"l":2},{"l":2},{"l":2},{"l":2},{"l":2},{},{"l":67},{"l":67},{"l":67},{"l":67},{"l":67},{"l":64},{"l":2},{"l":2},{"l":2},{"l":2},{"l":2},{"l":2},{},{"l":67},{"l":67},{"l":67},{"l":67},{"l":67},{"l":67},{},{"l":2},{"l":2},{"l":2},{"l":2},{"l":2},{},{},{"l":67},{"l":67},{"l":67},{"l":67},{"l":67},{"l":67},{"l":67},{},{"l":2},{"l":2},{"l":2},{},{},{"l":3},{"l":67},{"l":67},{"l":67},{"l":67},{"l":67},{"l":67},{"l":67},{},{},{"l":2},{"l":2},{},{"l":3},{"l":67},{"l":67},{"l":67},{"l":67},{"l":67},{"l":67},{"l":67},{"l":67},{"l":3},{},{},{},{"l":3},{"l":3},{"l":2},{"l":67},{"l":67},{"l":67},{"l":67},{"l":67},{"l":67},{"l":67},{"l":67},{"l":67},{},{"l":2},{},{"l":3},{"l":2},{"l":67},{"l":67},{"l":67},{"l":67},{"l":67},{"l":67},{"l":67},{"l":67},{"l":67},{"l":67},{"l":2},{},{"l":67},{"l":67},{"l":67},{"l":67},{"l":67},{"l":67},{"l":67},{"l":67},{"l":67},{"l":67},{"l":67},{"l":3},{"l":2},{"l":2},{},{"l":67},{"l":67},{"l":67},{"l":67},{"l":3},{"l":67},{"l":67},{"l":67},{"l":67},{"l":67},{"l":3},{"l":2},{"l":2},{"l":64},{"l":64},{"l":67},{"l":67},{"l":3},{"l":3},{"l":67},{"l":67},{"l":67},{"l":67},{"l":2},{"l":2},{"l":2},{"l":2},{"l":2},{"l":64},{"l":64},{"l":67},{"l":3},{"l":3},{"l":67},{"l":67},{"l":67},{"l":3},{"l":2},{"l":2},{"l":2},{"l":2},{"l":2},{"l":2},{},{"l":67},{"l":3},{"l":3},{"l":2},{"l":2},{"l":3},{"l":2},{"l":2},{"l":2},{"l":2},{"l":2},{"l":2},{"l":2},{"l":2},{},{"l":3},{"l":3},{"l":2},{"l":2},{"l":2},{"l":3},{"l":2},{"l":2},{"l":2},{"l":2},{"l":2},{"l":2},{"l":2},{},{"l":3},{"l":3},{"l":2},{"l":2},{"l":3},{"l":67},{"l":2},{"l":2},{"l":2},{"l":2},{"l":2},{"l":2},{"l":2},{"l":2},{},{"l":3},{"l":3},{"l":3},{"l":67},{"l":67},{"l":2},{"l":2},{"l":2},{"l":2},{"l":2},{"l":2},{"l":2},{"l":2},{},{},{"l":3},{"l":67},{"l":67},{"l":2},{"l":2},{"l":2},{"l":2},{"l":2},{"l":2},{"l":2},{"l":2},{"l":2},{"l":2},{},{},{"l":3},{"l":3},{"l":3},{"l":2},{"l":2},{"l":2},{"l":2},{"l":2},{"l":2},{"l":2},{"l":2},{"l":2},{"l":2},{},{"l":3},{"l":3},{"l":2},{"l":2},{"l":2}],"midgroundLayer":{"229":[{"g":66190,"x":543,"y":73,"hue":[-39,-44,-57],"sx":-1,"id":512407,"cw":264,"ch":265}],"231":[{"g":57968,"x":862,"y":-212,"hue":[-107,-104,-103],"sx":-1,"cw":766,"ch":679}],"236":[{"g":202647,"x":981,"y":-92,"hue":[11,1,-17],"cy":-77,"cw":233,"ch":424}],"238":[{"g":202654,"x":436,"y":-59.5,"hue":[-64,-66,-70],"sx":-1,"cw":517,"ch":515}],"242":[{"g":65704,"x":347,"y":375.5,"hue":[-45,-45,-45],"cw":81,"ch":37}],"243":[{"g":65704,"x":413,"y":313.5,"hue":[-45,-45,-45],"cw":81,"ch":37}],"246":[{"g":61018,"x":1007,"y":290.5,"hue":[-10,-19,-47],"sx":-1,"id":512408,"cw":295,"ch":127},{"g":202428,"x":769,"y":327.5,"hue":[14,3,-16],"cw":123,"ch":71},{"g":60356,"x":528,"y":213.5,"hue":[-44,-14,-6],"cw":361,"ch":142}],"252":[{"g":202674,"x":-278,"y":67,"hue":[-59,-61,-63],"cw":429,"ch":420}],"257":[{"g":203801,"x":359,"y":11,"hue":[0,0,0],"cw":268,"ch":393}],"270":[{"g":202385,"x":377,"y":385.5,"hue":[-60,-60,-60],"cw":81,"ch":38},{"look":686,"x":373,"y":411.5,"hue":[0,0,0],"sx":-1,"id":512684}],"274":[{"g":202445,"x":715,"y":326.5,"hue":[8,-2,-19],"cw":286,"ch":130}],"275":[{"g":202445,"x":801,"y":326.5,"hue":[11,1,-17],"cw":286,"ch":130}],"276":[{"g":202437,"x":830,"y":197.5,"hue":[11,1,-18],"cw":139,"ch":93}],"277":[{"g":60356,"x":786,"y":256.5,"hue":[-44,-14,-6],"cw":361,"ch":142}],"290":[{"g":202429,"x":914,"y":162,"hue":[8,-1,-19],"cw":112,"ch":67}],"304":[{"g":202653,"x":897,"y":25.5,"hue":[-20,-24,-43],"cw":317,"ch":525}],"318":[{"g":202398,"x":829,"y":352,"hue":[-27,-19,-28],"cw":153,"ch":156}],"322":[{"g":202444,"x":17,"y":421.5,"hue":[-35,-37,-45],"cw":225,"ch":95}],"323":[{"g":202366,"x":-23,"y":-216.5,"hue":[-29,-33,-41],"cy":-201,"cw":214,"ch":528},{"g":202371,"x":117,"y":305.5,"hue":[-29,-33,-41],"cw":96,"ch":206},{"g":202445,"x":113,"y":412.5,"hue":[-29,-33,-41],"cw":286,"ch":130}],"324":[{"g":202368,"x":126,"y":-147.5,"hue":[-25,-29,-39],"cw":221,"ch":659},{"g":60356,"x":12,"y":342.5,"hue":[-44,-14,-6],"cw":361,"ch":142}],"337":[{"g":202447,"x":45,"y":460,"hue":[-33,-36,-43],"cw":217,"ch":95}],"347":[{"g":61003,"x":922,"y":461,"hue":[-36,-41,-52],"cw":83,"ch":77}],"349":[{"g":202445,"x":1099,"y":473,"hue":[-34,-38,-50],"cw":286,"ch":130}],"360":[{"g":202449,"x":907,"y":486.5,"hue":[-14,-11,-16],"cw":225,"ch":95}],"362":[{"g":201909,"x":1024,"y":314.5,"hue":[-35,-33,-32],"cw":170,"ch":251}],"376":[{"g":202447,"x":1006,"y":503,"hue":[-14,-15,-22],"cw":217,"ch":95}],"381":[{"g":60638,"x":334,"y":533.5,"hue":[-16,-20,-41],"sx":-1,"cw":78,"ch":73}],"395":[{"g":61006,"x":218,"y":579,"hue":[-30,-34,-41],"cw":88,"ch":49}],"409":[{"g":57968,"x":561,"y":67.5,"hue":[-107,-104,-103],"sx":-1,"cw":766,"ch":679}],"434":[{"g":202654,"x":287,"y":431.5,"hue":[-54,-56,-60],"sx":-1,"cw":517,"ch":515}],"484":[{"g":202442,"x":662,"y":669,"hue":[-14,-22,-36],"cw":263,"ch":107}],"495":[{"g":61015,"x":479,"y":670.5,"hue":[-46,-47,-64],"sx":-1,"id":512405,"cw":371,"ch":180}],"560":[{"g":202368,"x":-132,"y":260.5,"hue":[-63,-62,-62],"cw":221,"ch":659},{"g":202371,"x":-70,"y":735.5,"hue":[-71,-70,-67],"cw":96,"ch":206},{"g":202370,"x":-27,"y":583.5,"hue":[-77,-74,-70],"cw":132,"ch":267},{"g":202429,"x":355,"y":742.5,"hue":[-26,-36,-54],"cw":112,"ch":67},{"g":202674,"x":962,"y":672.5,"hue":[-51,-53,-59],"cw":429,"ch":420},{"g":202654,"x":319,"y":642.5,"hue":[-56,-55,-59],"cw":517,"ch":515},{"g":202437,"x":271,"y":820.5,"hue":[-19,-29,-48],"cw":139,"ch":93},{"g":202491,"x":-512,"y":438.5,"hue":[0,0,0],"cx":-459,"cw":1267,"ch":412},{"g":41872,"x":650,"y":345.5,"hue":[0,0,0],"sx":1.301,"sy":1.301,"cx":541,"cy":277.5,"cw":975,"ch":666},{"g":41872,"x":650,"y":345.5,"hue":[0,0,0],"sx":1.301,"sy":1.301,"alpha":0.5647058823529412,"cx":541,"cy":277.5,"cw":975,"ch":666}]},"atlasLayout":{"width":1345,"height":1877,"graphicsPositions":{"41872":{"sx":555,"sy":1634,"sw":212,"sh":145,"cx":100,"cy":171,"cw":975,"ch":666},"57968":{"sx":1,"sy":1,"sw":766,"sh":679},"60356":{"sx":769,"sy":1713,"sw":233,"sh":92,"cw":361,"ch":142},"60638":{"sx":769,"sy":597,"sw":78,"sh":73},"61003":{"sx":1088,"sy":427,"sw":83,"sh":77},"61006":{"sx":849,"sy":597,"sw":88,"sh":49},"61015":{"sx":267,"sy":1425,"sw":371,"sh":180},"61018":{"sx":907,"sy":1584,"sw":295,"sh":127},"65704":{"sx":84,"sy":1801,"sw":81,"sh":37},"66190":{"sx":1,"sy":1425,"sw":264,"sh":265},"201909":{"sx":1174,"sy":427,"sw":170,"sh":251},"202366":{"sx":691,"sy":1104,"sw":214,"sh":528,"cy":201},"202368":{"sx":951,"sy":528,"sw":221,"sh":659},"202370":{"sx":1174,"sy":680,"sw":132,"sh":267},"202371":{"sx":1177,"sy":1107,"sw":96,"sh":206},"202385":{"sx":1,"sy":1801,"sw":81,"sh":38},"202398":{"sx":1174,"sy":949,"sw":153,"sh":156},"202428":{"sx":769,"sy":1634,"sw":123,"sh":71},"202429":{"sx":769,"sy":528,"sw":112,"sh":67},"202437":{"sx":520,"sy":1104,"sw":139,"sh":93},"202442":{"sx":1,"sy":1692,"sw":263,"sh":107},"202444":{"sx":266,"sy":1739,"sw":225,"sh":95},"202445":{"sx":267,"sy":1607,"sw":286,"sh":130},"202447":{"sx":493,"sy":1781,"sw":217,"sh":95},"202449":{"sx":1004,"sy":1713,"sw":225,"sh":95},"202491":{"sx":1,"sy":1199,"sw":688,"sh":224,"cx":459,"cw":1267,"ch":412},"202647":{"sx":1088,"sy":1,"sw":233,"sh":424,"cy":77},"202653":{"sx":769,"sy":1,"sw":317,"sh":525},"202654":{"sx":1,"sy":682,"sw":517,"sh":515},"202674":{"sx":520,"sy":682,"sw":429,"sh":420},"203801":{"sx":907,"sy":1189,"sw":268,"sh":393}}}}