{"id":142082565,"topNeighbourId":142082564,"bottomNeighbourId":142082566,"leftNeighbourId":142082053,"rightNeighbourId":142083077,"shadowBonusOnEntities":-1,"cells":[{"l":2},{"l":2},{"l":2},{"l":2},{"l":2},{"l":2},{"l":2},{"l":2},{"l":2},{"l":66},{"l":66},{"l":66},{"l":66},{"l":66},{"l":2},{"l":2},{"l":2},{"l":2},{"l":2},{"l":2},{"l":2},{"l":2},{"l":2},{"l":66},{"l":66},{"l":66},{"l":66},{"l":66},{"l":2},{"l":2},{"l":2},{"l":2},{"l":2},{"l":2},{"l":2},{"l":2},{"l":2},{"l":2},{"l":66},{"l":66},{"l":66},{"l":66},{"l":2},{"l":2},{"l":2},{"l":2},{"l":2},{"l":2},{"l":2},{"l":2},{"l":2},{"l":66},{"l":66},{"l":66},{"l":66},{"l":66},{"l":2},{"l":2},{"l":2},{"l":2},{"l":2},{"l":2},{"l":2},{"l":2},{"l":2},{"l":2},{"l":66},{"l":66},{"l":66},{"l":66},{"l":2},{"l":2},{"l":2},{"l":2},{"l":2},{"l":2},{"l":2},{"l":2},{"l":2},{"l":66},{"l":66},{"l":66},{"l":66},{"l":66},{"l":2},{"l":2},{"l":2},{"l":2},{"l":2},{"l":2},{"l":2},{"l":2},{"l":2},{"l":2},{"l":2},{"l":66},{"l":66},{"l":66},{"l":2},{"l":2},{"l":2},{"l":2},{"l":2},{"l":2},{"l":2},{"l":2},{"l":2},{"l":2},{"l":2},{"l":66},{"l":66},{"l":66},{"l":2},{"l":2},{"l":2},{"l":2},{"l":2},{"l":2},{"l":2},{"l":2},{"l":2},{"l":2},{"l":2},{"l":66},{"l":66},{"l":66},{"l":2},{"l":2},{"l":2},{"l":2},{"l":2},{"l":2},{"l":2},{"l":2},{"l":2},{"l":2},{"l":2},{"l":2},{"l":66},{"l":66},{"l":2},{"l":2},{"l":2},{"l":2},{"l":2},{"l":2},{"l":2},{"l":2},{"l":2},{"l":2},{"l":2},{"l":2},{"l":66},{"l":66},{"l":2},{"l":2},{"l":2},{"l":2},{"l":2},{"l":2},{"l":66},{"l":2},{"l":2},{"l":2},{"l":2},{"l":66},{"l":66},{"l":66},{"l":2},{"l":2},{"l":2},{"l":2},{"l":2},{"l":66},{"l":66},{"l":66},{"l":2},{"l":2},{"l":2},{"l":2},{"l":66},{"l":66},{"l":2},{"l":2},{"l":2},{"l":2},{"l":2},{"l":2},{"l":66},{"l":2},{"l":2},{"l":2},{"l":2},{"l":66},{"l":66},{"l":66},{"l":2},{"l":2},{"l":2},{"l":2},{"l":2},{"l":2},{"l":2},{"l":66},{"l":2},{"l":2},{"l":2},{"l":2},{"l":66},{"l":66},{"l":2},{"l":2},{"l":2},{"l":2},{"l":2},{"l":66},{"l":2},{"l":2},{"l":2},{"l":2},{"l":66},{"l":66},{"l":66},{"l":66},{"l":2},{"l":2},{"l":2},{"l":2},{"l":2},{"l":3},{"l":67},{"l":66},{"l":2},{"l":2},{"l":66},{"l":66},{"l":66},{"l":66},{"l":2},{"l":2},{"l":2},{"l":2},{"l":3},{"l":67},{"l":67},{"l":2},{"l":2},{"l":66},{"l":66},{"l":66},{"l":66},{"l":66},{"l":2},{"l":2},{"l":2},{"l":2},{"l":67},{"l":67},{"l":67},{"l":67},{"l":66},{"l":3},{"l":66},{"l":66},{"l":66},{"l":66},{"l":2},{"l":2},{"l":3},{"l":67},{"l":67},{"l":67},{"l":67},{"l":67},{"l":67},{"l":67},{"l":66},{"l":66},{"l":66},{"l":66},{"l":2},{"l":2},{"l":67},{"l":67},{"l":67},{"l":67},{"l":67},{"l":67},{"l":67},{"l":67},{"l":67},{"l":66},{"l":66},{"l":66},{"l":2},{"l":3},{"l":67},{"l":67},{"l":67},{"l":67},{"l":67},{"l":67},{"l":67},{"l":67},{"l":67},{"l":66},{"l":66},{"l":66},{"l":2},{"l":2},{"l":67},{"l":67},{"l":67},{"l":67},{"l":67},{"l":67},{"l":67},{"l":67},{"l":67},{"l":67},{"l":66},{"l":66},{"l":2},{"l":66},{"l":67},{"l":67},{"l":67},{"l":67},{"l":67},{"l":67},{"l":67},{"l":67},{"l":67},{"l":66},{"l":66},{"l":66},{"l":2},{"l":2},{"l":67},{"l":67},{"l":67},{"l":67},{"l":67},{"l":67},{"l":67},{"l":2},{"l":67},{"l":67},{"l":66},{"l":66},{"l":2},{"l":67},{"l":67},{"l":67},{"l":67},{"l":67},{"l":67},{"l":67},{"l":66},{"l":2},{"l":67},{"l":66},{"l":66},{"l":66},{"l":2},{"l":67},{"l":67},{"l":67},{"l":67},{"l":67},{"l":67},{"l":67},{"l":67},{"l":67},{"l":67},{"l":66},{"l":66},{"l":66},{"l":2},{"l":67},{"l":67},{"l":67},{"l":67},{"l":67},{"l":67},{"l":67},{"l":67},{"l":67},{"l":67},{"l":66},{"l":66},{"l":66},{"l":2},{"l":66},{"l":67},{"l":67},{"l":2},{"l":67},{"l":67},{"l":67},{"l":67},{"l":67},{"l":67},{"l":3},{"l":66},{"l":66},{"l":2},{"l":66},{"l":67},{"l":67},{"l":67},{"l":67},{"l":67},{"l":67},{"l":67},{"l":67},{"l":3},{"l":2},{"l":66},{"l":66},{"l":2},{"l":66},{"l":66},{"l":67},{"l":67},{"l":67},{"l":67},{"l":67},{"l":67},{"l":67},{"l":3},{"l":2},{"l":66},{"l":66},{"l":2},{"l":66},{"l":66},{"l":67},{"l":67},{"l":67},{"l":67},{"l":67},{"l":3},{"l":3},{"l":2},{"l":2},{"l":66},{"l":66},{"l":2},{"l":2},{"l":66},{"l":66},{"l":67},{"l":67},{"l":67},{"l":67},{"l":67},{"l":3},{"l":2},{"l":2},{"l":2},{"l":66},{"l":2},{"l":66},{"l":2},{"l":66},{"l":67},{"l":67},{"l":67},{"l":67},{"l":3},{"l":2},{"l":2},{"l":2},{"l":2},{"l":66},{"l":2},{"l":2},{"l":2},{"l":2},{"l":66},{"l":67},{"l":67},{"l":67},{"l":67},{"l":2},{"l":2},{"l":2},{"l":2},{"l":66},{"l":2},{"l":2},{"l":2},{"l":2},{"l":66},{"l":67},{"l":67},{"l":67},{"l":2},{"l":2},{"l":2},{"l":2},{"l":2},{"l":66},{"l":2},{"l":2},{"l":2},{"l":2},{"l":2},{"l":66},{"l":3},{"l":66},{"l":66},{"l":2},{"l":2},{"l":2},{"l":2},{"l":66},{"l":2},{"l":2},{"l":2},{"l":2},{"l":66},{"l":2},{"l":2},{"l":66},{"l":2},{"l":2},{"l":2},{"l":2},{"l":2},{"l":66},{"l":2},{"l":2},{"l":2},{"l":2},{"l":2},{"l":2},{"l":2},{"l":2},{"l":2},{"l":2},{"l":2},{"l":2},{"l":2},{"l":66},{"l":2},{"l":2},{"l":2},{"l":2},{"l":2},{"l":2},{"l":2},{"l":2},{"l":2},{"l":2},{"l":2},{"l":2},{"l":2},{"l":66}],"midgroundLayer":{"232":[{"g":201796,"x":621,"y":246,"hue":[0,0,0],"cw":134,"ch":127}],"238":[{"g":202647,"x":71,"y":-46.5,"hue":[-39,-41,-66],"sx":-1,"cy":-31,"cw":124,"ch":470}],"239":[{"g":32121,"x":288,"y":-100.5,"hue":[0,0,0],"sx":-1,"cy":-85,"cw":291,"ch":318}],"240":[{"g":201796,"x":170,"y":289.5,"hue":[0,0,0],"cw":134,"ch":127}],"241":[{"g":51644,"x":314,"y":350.5,"hue":[-30,-30,-30],"cw":68,"ch":40}],"245":[{"g":13649,"x":596,"y":284.5,"hue":[0,0,0],"cw":98,"ch":111}],"246":[{"g":203731,"x":1015,"y":103.5,"hue":[0,0,0],"sx":-1,"cw":428,"ch":349},{"g":51646,"x":692,"y":337.5,"hue":[-47,-49,-62],"cw":94,"ch":69}],"254":[{"g":51646,"x":143,"y":359,"hue":[-35,-35,-35],"cw":94,"ch":69}],"260":[{"g":10348,"x":665,"y":326,"hue":[-50,-50,-50],"cw":80,"ch":70}],"271":[{"g":203743,"x":243,"y":-103.5,"hue":[0,0,0],"cy":-88,"cw":530,"ch":280}],"322":[{"g":201796,"x":-2,"y":418.5,"hue":[0,0,0],"cw":134,"ch":127}],"336":[{"g":203731,"x":198,"y":254,"hue":[0,0,0],"sx":-1,"cw":428,"ch":349}],"358":[{"g":61003,"x":751,"y":479.5,"hue":[4,2,-17],"cw":83,"ch":77},{"g":700399,"x":784,"y":503.5,"hue":[4,2,-17],"sx":-1,"cw":90,"ch":50}],"396":[{"g":10457,"x":302,"y":550,"hue":[25,25,25],"cw":80,"ch":70}],"449":[{"g":50587,"x":596,"y":-468,"hue":[0,0,0],"sx":-1,"cy":-453,"cw":649,"ch":773}],"458":[{"g":203794,"x":1106,"y":560,"hue":[0,0,0],"sx":-1,"id":512765,"cw":376,"ch":291}],"498":[{"g":203795,"x":995,"y":624.5,"hue":[0,0,0],"sx":-1,"cw":288,"ch":226}],"560":[{"g":201914,"x":-1249,"y":580,"hue":[0,0,0],"cx":-637,"cw":1374,"ch":271},{"g":201914,"x":-690,"y":646.5,"hue":[0,0,0],"cx":-637,"cw":1374,"ch":271},{"g":61006,"x":1078,"y":824.5,"hue":[0,0,0],"cw":88,"ch":26},{"g":202649,"x":231,"y":321.5,"hue":[-72,-73,-89],"sx":-1,"cw":284,"ch":529}]},"atlasLayout":{"width":1523,"height":633,"graphicsPositions":{"10348":{"sx":168,"sy":532,"sw":80,"sh":70},"10457":{"sx":86,"sy":532,"sw":80,"sh":70},"13649":{"sx":1239,"sy":358,"sw":98,"sh":111},"32121":{"sx":819,"sy":294,"sw":291,"sh":318,"cy":85},"50587":{"sx":1112,"sy":229,"sw":125,"sh":149,"cy":453,"cw":649,"ch":773},"51644":{"sx":1112,"sy":556,"sw":68,"sh":40},"51646":{"sx":1112,"sy":380,"sw":94,"sh":69},"61003":{"sx":1,"sy":532,"sw":83,"sh":77},"61006":{"sx":86,"sy":604,"sw":88,"sh":26},"201796":{"sx":1239,"sy":229,"sw":134,"sh":127},"201914":{"sx":1112,"sy":473,"sw":410,"sh":81,"cx":637,"cw":1374,"ch":271},"202647":{"sx":1385,"sy":1,"sw":124,"sh":470,"cy":31},"202649":{"sx":1,"sy":1,"sw":284,"sh":529},"203731":{"sx":287,"sy":1,"sw":428,"sh":349},"203743":{"sx":287,"sy":352,"sw":530,"sh":280,"cy":88},"203794":{"sx":717,"sy":1,"sw":376,"sh":291},"203795":{"sx":1095,"sy":1,"sw":288,"sh":226},"700399":{"sx":717,"sy":294,"sw":90,"sh":50}}}}